{
"meta":{"test_sets":[],"test_metrics":[],"learn_metrics":[{"best_value":"Min","name":"MultiClass"}],"launch_mode":"Train","parameters":"","iteration_count":1000,"learn_sets":["learn"],"name":"experiment"},
"iterations":[
{"learn":[1.089628646],"iteration":0,"passed_time":0.08122200526,"remaining_time":81.14078325},
{"learn":[1.081725771],"iteration":1,"passed_time":0.09908036926,"remaining_time":49.44110426},
{"learn":[1.076709704],"iteration":2,"passed_time":0.116695908,"remaining_time":38.7819401},
{"learn":[1.068543492],"iteration":3,"passed_time":0.1347647234,"remaining_time":33.55641611},
{"learn":[1.063002472],"iteration":4,"passed_time":0.1536418868,"remaining_time":30.57473547},
{"learn":[1.05510274],"iteration":5,"passed_time":0.174028125,"remaining_time":28.83065937},
{"learn":[1.050236545],"iteration":6,"passed_time":0.1917795342,"remaining_time":27.20529678},
{"learn":[1.045751849],"iteration":7,"passed_time":0.2098200172,"remaining_time":26.01768213},
{"learn":[1.040632191],"iteration":8,"passed_time":0.2280199948,"remaining_time":25.10753498},
{"learn":[1.037089745],"iteration":9,"passed_time":0.2461381002,"remaining_time":24.36767192},
{"learn":[1.033607942],"iteration":10,"passed_time":0.263710557,"remaining_time":23.70997645},
{"learn":[1.031573061],"iteration":11,"passed_time":0.2811421019,"remaining_time":23.14736639},
{"learn":[1.027523656],"iteration":12,"passed_time":0.2990606306,"remaining_time":22.70560326},
{"learn":[1.024883047],"iteration":13,"passed_time":0.3173941871,"remaining_time":22.35361918},
{"learn":[1.023609661],"iteration":14,"passed_time":0.3365812152,"remaining_time":22.10216647},
{"learn":[1.020811981],"iteration":15,"passed_time":0.3557177867,"remaining_time":21.87664388},
{"learn":[1.017900845],"iteration":16,"passed_time":0.3739285973,"remaining_time":21.62187124},
{"learn":[1.015468661],"iteration":17,"passed_time":0.393499196,"remaining_time":21.46756725},
{"learn":[1.014097764],"iteration":18,"passed_time":0.4140848026,"remaining_time":21.37985217},
{"learn":[1.01296509],"iteration":19,"passed_time":0.4318841269,"remaining_time":21.16232222},
{"learn":[1.010463093],"iteration":20,"passed_time":0.449829238,"remaining_time":20.97061067},
{"learn":[1.00864562],"iteration":21,"passed_time":0.4674661927,"remaining_time":20.78099711},
{"learn":[1.00641911],"iteration":22,"passed_time":0.4852864746,"remaining_time":20.61412547},
{"learn":[1.00420355],"iteration":23,"passed_time":0.5028442236,"remaining_time":20.44899843},
{"learn":[1.002724974],"iteration":24,"passed_time":0.5210381598,"remaining_time":20.32048823},
{"learn":[1.001164941],"iteration":25,"passed_time":0.543508412,"remaining_time":20.36066128},
{"learn":[0.999507094],"iteration":26,"passed_time":0.5699684481,"remaining_time":20.53997407},
{"learn":[0.9987054332],"iteration":27,"passed_time":0.5944922986,"remaining_time":20.63737551},
{"learn":[0.9970654692],"iteration":28,"passed_time":0.6186676607,"remaining_time":20.71469995},
{"learn":[0.9955186248],"iteration":29,"passed_time":0.6422320431,"remaining_time":20.76550273},
{"learn":[0.9931549788],"iteration":30,"passed_time":0.6628979387,"remaining_time":20.72090654},
{"learn":[0.9920009115],"iteration":31,"passed_time":0.684623799,"remaining_time":20.70986992},
{"learn":[0.9901864117],"iteration":32,"passed_time":0.7049962877,"remaining_time":20.65852758},
{"learn":[0.9884357736],"iteration":33,"passed_time":0.7246915905,"remaining_time":20.58976695},
{"learn":[0.987407914],"iteration":34,"passed_time":0.7467128993,"remaining_time":20.58794137},
{"learn":[0.9859383259],"iteration":35,"passed_time":0.7677735318,"remaining_time":20.55926902},
{"learn":[0.9843380858],"iteration":36,"passed_time":0.7889969504,"remaining_time":20.53524495},
{"learn":[0.9833519723],"iteration":37,"passed_time":0.8091619877,"remaining_time":20.48457453},
{"learn":[0.9821207893],"iteration":38,"passed_time":0.8309342214,"remaining_time":20.47507146},
{"learn":[0.980909112],"iteration":39,"passed_time":0.8506231912,"remaining_time":20.41495659},
{"learn":[0.9795368909],"iteration":40,"passed_time":0.8703694924,"remaining_time":20.35815471},
{"learn":[0.9784436093],"iteration":41,"passed_time":0.889220865,"remaining_time":20.28270449},
{"learn":[0.9774755282],"iteration":42,"passed_time":0.9074138845,"remaining_time":20.19523459},
{"learn":[0.9762356014],"iteration":43,"passed_time":0.9259461011,"remaining_time":20.11828347},
{"learn":[0.9750180345],"iteration":44,"passed_time":0.9441550784,"remaining_time":20.03706889},
{"learn":[0.9740079447],"iteration":45,"passed_time":0.9615363333,"remaining_time":19.94142743},
{"learn":[0.9726797772],"iteration":46,"passed_time":0.9798508905,"remaining_time":19.8680404},
{"learn":[0.9716620166],"iteration":47,"passed_time":0.9970840253,"remaining_time":19.77549983},
{"learn":[0.9703293162],"iteration":48,"passed_time":1.01490814,"remaining_time":19.69750289},
{"learn":[0.9690112199],"iteration":49,"passed_time":1.033378109,"remaining_time":19.63418407},
{"learn":[0.9682737551],"iteration":50,"passed_time":1.052996581,"remaining_time":19.59399521},
{"learn":[0.9669886026],"iteration":51,"passed_time":1.074602737,"remaining_time":19.59083452},
{"learn":[0.9660293818],"iteration":52,"passed_time":1.095053515,"remaining_time":19.56633356},
{"learn":[0.9651902135],"iteration":53,"passed_time":1.114811024,"remaining_time":19.52983757},
{"learn":[0.9642039539],"iteration":54,"passed_time":1.134866523,"remaining_time":19.49907026},
{"learn":[0.9633247466],"iteration":55,"passed_time":1.153318409,"remaining_time":19.44165318},
{"learn":[0.9626002827],"iteration":56,"passed_time":1.171310019,"remaining_time":19.37798856},
{"learn":[0.9618973121],"iteration":57,"passed_time":1.188991805,"remaining_time":19.31086691},
{"learn":[0.9610846799],"iteration":58,"passed_time":1.206905667,"remaining_time":19.24912259},
{"learn":[0.9602342],"iteration":59,"passed_time":1.224703283,"remaining_time":19.18701811},
{"learn":[0.9594852173],"iteration":60,"passed_time":1.243267166,"remaining_time":19.13816178},
{"learn":[0.9582305082],"iteration":61,"passed_time":1.26480799,"remaining_time":19.13532089},
{"learn":[0.9574473389],"iteration":62,"passed_time":1.283366373,"remaining_time":19.08752843},
{"learn":[0.9567682187],"iteration":63,"passed_time":1.301914339,"remaining_time":19.04049721},
{"learn":[0.9563163838],"iteration":64,"passed_time":1.321536019,"remaining_time":19.00978735},
{"learn":[0.9549614883],"iteration":65,"passed_time":1.340623676,"remaining_time":18.97185626},
{"learn":[0.9539759327],"iteration":66,"passed_time":1.361247531,"remaining_time":18.9558798},
{"learn":[0.9533515672],"iteration":67,"passed_time":1.383802697,"remaining_time":18.96623696},
{"learn":[0.9525782054],"iteration":68,"passed_time":1.402832564,"remaining_time":18.92807416},
{"learn":[0.9519590514],"iteration":69,"passed_time":1.422677362,"remaining_time":18.90128495},
{"learn":[0.9511174391],"iteration":70,"passed_time":1.445084866,"remaining_time":18.9082231},
{"learn":[0.9501108728],"iteration":71,"passed_time":1.465664223,"remaining_time":18.89078331},
{"learn":[0.9494397555],"iteration":72,"passed_time":1.489554677,"remaining_time":18.91530392},
{"learn":[0.948684834],"iteration":73,"passed_time":1.511070628,"remaining_time":18.90880272},
{"learn":[0.9480211155],"iteration":74,"passed_time":1.532245923,"remaining_time":18.89769972},
{"learn":[0.9471610488],"iteration":75,"passed_time":1.553461551,"remaining_time":18.88682201},
{"learn":[0.9461942735],"iteration":76,"passed_time":1.574534058,"remaining_time":18.8739602},
{"learn":[0.9452377569],"iteration":77,"passed_time":1.596086507,"remaining_time":18.86656102},
{"learn":[0.9442891766],"iteration":78,"passed_time":1.616311001,"remaining_time":18.84332192},
{"learn":[0.9433422709],"iteration":79,"passed_time":1.635151707,"remaining_time":18.80424463},
{"learn":[0.9424904766],"iteration":80,"passed_time":1.654886342,"remaining_time":18.77580924},
{"learn":[0.9418049766],"iteration":81,"passed_time":1.67358222,"remaining_time":18.73595705},
{"learn":[0.94138439],"iteration":82,"passed_time":1.695196875,"remaining_time":18.72886186},
{"learn":[0.9402044469],"iteration":83,"passed_time":1.714504774,"remaining_time":18.69626635},
{"learn":[0.9395167177],"iteration":84,"passed_time":1.733359939,"remaining_time":18.65910993},
{"learn":[0.9390440618],"iteration":85,"passed_time":1.751119681,"remaining_time":18.61073707},
{"learn":[0.938117338],"iteration":86,"passed_time":1.768809884,"remaining_time":18.56233821},
{"learn":[0.9370507327],"iteration":87,"passed_time":1.786476504,"remaining_time":18.51439286},
{"learn":[0.9361726441],"iteration":88,"passed_time":1.804310327,"remaining_time":18.46883942},
{"learn":[0.935673745],"iteration":89,"passed_time":1.821599377,"remaining_time":18.4183937},
{"learn":[0.9347053056],"iteration":90,"passed_time":1.839644193,"remaining_time":18.37622606},
{"learn":[0.9339099245],"iteration":91,"passed_time":1.858687184,"remaining_time":18.34443439},
{"learn":[0.933022296],"iteration":92,"passed_time":1.878454318,"remaining_time":18.31997921},
{"learn":[0.932293468],"iteration":93,"passed_time":1.899255751,"remaining_time":18.30559266},
{"learn":[0.9312474198],"iteration":94,"passed_time":1.920904739,"remaining_time":18.29914514},
{"learn":[0.9306349667],"iteration":95,"passed_time":1.940354633,"remaining_time":18.2716728},
{"learn":[0.9298479735],"iteration":96,"passed_time":1.96182321,"remaining_time":18.26315834},
{"learn":[0.9286288325],"iteration":97,"passed_time":1.982996506,"remaining_time":18.25166172},
{"learn":[0.9280293979],"iteration":98,"passed_time":2.003178876,"remaining_time":18.23095118},
{"learn":[0.9271581555],"iteration":99,"passed_time":2.024020682,"remaining_time":18.21618614},
{"learn":[0.9265421352],"iteration":100,"passed_time":2.044235926,"remaining_time":18.19572374},
{"learn":[0.9258181272],"iteration":101,"passed_time":2.063856315,"remaining_time":18.17002912},
{"learn":[0.9249645204],"iteration":102,"passed_time":2.084564292,"remaining_time":18.15392398},
{"learn":[0.9234877995],"iteration":103,"passed_time":2.104767536,"remaining_time":18.13338185},
{"learn":[0.9225181018],"iteration":104,"passed_time":2.131200448,"remaining_time":18.16594668},
{"learn":[0.9216677524],"iteration":105,"passed_time":2.15272544,"remaining_time":18.15600513},
{"learn":[0.9208119697],"iteration":106,"passed_time":2.173182176,"remaining_time":18.13693162},
{"learn":[0.9201001404],"iteration":107,"passed_time":2.193521916,"remaining_time":18.1168662},
{"learn":[0.9188889447],"iteration":108,"passed_time":2.212253876,"remaining_time":18.08365324},
{"learn":[0.9180750035],"iteration":109,"passed_time":2.229938579,"remaining_time":18.04223032},
{"learn":[0.9173456675],"iteration":110,"passed_time":2.247056218,"remaining_time":17.99669349},
{"learn":[0.9159497013],"iteration":111,"passed_time":2.264573385,"remaining_time":17.95483184},
{"learn":[0.9150516374],"iteration":112,"passed_time":2.284873668,"remaining_time":17.93524728},
{"learn":[0.9139419225],"iteration":113,"passed_time":2.304612802,"remaining_time":17.91128897},
{"learn":[0.9130776949],"iteration":114,"passed_time":2.325029331,"remaining_time":17.89261703},
{"learn":[0.9122088688],"iteration":115,"passed_time":2.343023066,"remaining_time":17.85545164},
{"learn":[0.9111056187],"iteration":116,"passed_time":2.361905271,"remaining_time":17.82531926},
{"learn":[0.9104086264],"iteration":117,"passed_time":2.379520393,"remaining_time":17.78590666},
{"learn":[0.9094482356],"iteration":118,"passed_time":2.396661739,"remaining_time":17.74335287},
{"learn":[0.9085435235],"iteration":119,"passed_time":2.41505621,"remaining_time":17.71041221},
{"learn":[0.9078175987],"iteration":120,"passed_time":2.433767837,"remaining_time":17.68001594},
{"learn":[0.9066434381],"iteration":121,"passed_time":2.452166183,"remaining_time":17.64755663},
{"learn":[0.9059024241],"iteration":122,"passed_time":2.471149343,"remaining_time":17.61949572},
{"learn":[0.904932593],"iteration":123,"passed_time":2.490986641,"remaining_time":17.59761531},
{"learn":[0.9039293517],"iteration":124,"passed_time":2.511087389,"remaining_time":17.57761172},
{"learn":[0.9028497791],"iteration":125,"passed_time":2.531817908,"remaining_time":17.56197501},
{"learn":[0.9020043855],"iteration":126,"passed_time":2.550157797,"remaining_time":17.52982486},
{"learn":[0.9013704739],"iteration":127,"passed_time":2.569929556,"remaining_time":17.5076451},
{"learn":[0.9005786416],"iteration":128,"passed_time":2.589113626,"remaining_time":17.48153464},
{"learn":[0.8997399267],"iteration":129,"passed_time":2.60922754,"remaining_time":17.46175353},
{"learn":[0.898981412],"iteration":130,"passed_time":2.629419159,"remaining_time":17.44248282},
{"learn":[0.8978827971],"iteration":131,"passed_time":2.648726933,"remaining_time":17.4173862},
{"learn":[0.89730338],"iteration":132,"passed_time":2.668900679,"remaining_time":17.39802172},
{"learn":[0.8964790947],"iteration":133,"passed_time":2.690178429,"remaining_time":17.38578},
{"learn":[0.8957185463],"iteration":134,"passed_time":2.712777177,"remaining_time":17.38186858},
{"learn":[0.8949835823],"iteration":135,"passed_time":2.733715563,"remaining_time":17.36713417},
{"learn":[0.8940787898],"iteration":136,"passed_time":2.756980664,"remaining_time":17.36696579},
{"learn":[0.8933079231],"iteration":137,"passed_time":2.783439742,"remaining_time":17.38641346},
{"learn":[0.8924188615],"iteration":138,"passed_time":2.805050731,"remaining_time":17.37517036},
{"learn":[0.8916745147],"iteration":139,"passed_time":2.824540957,"remaining_time":17.3507516},
{"learn":[0.8908123771],"iteration":140,"passed_time":2.844156471,"remaining_time":17.32716602},
{"learn":[0.8898714266],"iteration":141,"passed_time":2.862815809,"remaining_time":17.2978589},
{"learn":[0.8890571764],"iteration":142,"passed_time":2.881177697,"remaining_time":17.26691809},
{"learn":[0.8883764121],"iteration":143,"passed_time":2.900028778,"remaining_time":17.23905996},
{"learn":[0.8876332899],"iteration":144,"passed_time":2.918099302,"remaining_time":17.20672347},
{"learn":[0.8867799968],"iteration":145,"passed_time":2.938526414,"remaining_time":17.18836683},
{"learn":[0.8858595577],"iteration":146,"passed_time":2.95792756,"remaining_time":17.16402863},
{"learn":[0.8850273439],"iteration":147,"passed_time":2.97636428,"remaining_time":17.13420518},
{"learn":[0.8844984398],"iteration":148,"passed_time":2.993490835,"remaining_time":17.09705168},
{"learn":[0.8837166213],"iteration":149,"passed_time":3.011644772,"remaining_time":17.06598704},
{"learn":[0.8828343308],"iteration":150,"passed_time":3.030564768,"remaining_time":17.03940058},
{"learn":[0.8821780854],"iteration":151,"passed_time":3.048135099,"remaining_time":17.00538529},
{"learn":[0.8815392924],"iteration":152,"passed_time":3.065733764,"remaining_time":16.97174182},
{"learn":[0.8804804305],"iteration":153,"passed_time":3.084239315,"remaining_time":16.9432887},
{"learn":[0.8799282196],"iteration":154,"passed_time":3.101721399,"remaining_time":16.9093844},
{"learn":[0.8793009854],"iteration":155,"passed_time":3.119330022,"remaining_time":16.87637525},
{"learn":[0.8787679542],"iteration":156,"passed_time":3.138637963,"remaining_time":16.85268664},
{"learn":[0.8780890075],"iteration":157,"passed_time":3.158064483,"remaining_time":16.82968541},
{"learn":[0.8772423119],"iteration":158,"passed_time":3.176767319,"remaining_time":16.80290135},
{"learn":[0.8763416497],"iteration":159,"passed_time":3.194804135,"remaining_time":16.77272171},
{"learn":[0.8755943363],"iteration":160,"passed_time":3.213509637,"remaining_time":16.74617755},
{"learn":[0.8748978415],"iteration":161,"passed_time":3.231514622,"remaining_time":16.7161065},
{"learn":[0.8741533001],"iteration":162,"passed_time":3.248779839,"remaining_time":16.68238482},
{"learn":[0.8735603666],"iteration":163,"passed_time":3.266656619,"remaining_time":16.6519813},
{"learn":[0.8728920618],"iteration":164,"passed_time":3.28474335,"remaining_time":16.62279211},
{"learn":[0.8723391774],"iteration":165,"passed_time":3.30332169,"remaining_time":16.59620656},
{"learn":[0.8716067124],"iteration":166,"passed_time":3.324715937,"remaining_time":16.58376273},
{"learn":[0.8709134199],"iteration":167,"passed_time":3.34465019,"remaining_time":16.56398189},
{"learn":[0.8705635805],"iteration":168,"passed_time":3.364524778,"remaining_time":16.54390586},
{"learn":[0.8696812886],"iteration":169,"passed_time":3.383802803,"remaining_time":16.52091957},
{"learn":[0.8692848249],"iteration":170,"passed_time":3.401674417,"remaining_time":16.49115843},
{"learn":[0.8687400653],"iteration":171,"passed_time":3.419852687,"remaining_time":16.46301177},
{"learn":[0.8679782717],"iteration":172,"passed_time":3.437858963,"remaining_time":16.43415816},
{"learn":[0.8670563702],"iteration":173,"passed_time":3.457343898,"remaining_time":16.41244862},
{"learn":[0.8663026063],"iteration":174,"passed_time":3.475044684,"remaining_time":16.38235351},
{"learn":[0.8654793707],"iteration":175,"passed_time":3.492540851,"remaining_time":16.35144126},
{"learn":[0.8647176319],"iteration":176,"passed_time":3.510283802,"remaining_time":16.32182808},
{"learn":[0.8641421021],"iteration":177,"passed_time":3.527990838,"remaining_time":16.29218241},
{"learn":[0.8637216465],"iteration":178,"passed_time":3.548680483,"remaining_time":16.27635015},
{"learn":[0.8631805854],"iteration":179,"passed_time":3.569149677,"remaining_time":16.25945964},
{"learn":[0.8626293756],"iteration":180,"passed_time":3.587858971,"remaining_time":16.23456628},
{"learn":[0.8621160904],"iteration":181,"passed_time":3.606224735,"remaining_time":16.20819688},
{"learn":[0.8614629172],"iteration":182,"passed_time":3.62428205,"remaining_time":16.1805379},
{"learn":[0.8605344214],"iteration":183,"passed_time":3.642547526,"remaining_time":16.15390642},
{"learn":[0.8598636779],"iteration":184,"passed_time":3.660384182,"remaining_time":16.12547626},
{"learn":[0.8593763377],"iteration":185,"passed_time":3.67753182,"remaining_time":16.09414463},
{"learn":[0.8587016359],"iteration":186,"passed_time":3.694686416,"remaining_time":16.06299495},
{"learn":[0.8581652483],"iteration":187,"passed_time":3.71214021,"remaining_time":16.03328644},
{"learn":[0.8576971524],"iteration":188,"passed_time":3.730324396,"remaining_time":16.00684172},
{"learn":[0.8570988772],"iteration":189,"passed_time":3.750012283,"remaining_time":15.98689447},
{"learn":[0.8563683709],"iteration":190,"passed_time":3.770489226,"remaining_time":15.97029206},
{"learn":[0.8557588896],"iteration":191,"passed_time":3.789354598,"remaining_time":15.94686727},
{"learn":[0.8552913975],"iteration":192,"passed_time":3.809069817,"remaining_time":15.92704323},
{"learn":[0.8546423031],"iteration":193,"passed_time":3.827690489,"remaining_time":15.90267286},
{"learn":[0.8540593282],"iteration":194,"passed_time":3.846462489,"remaining_time":15.87898617},
{"learn":[0.8536200277],"iteration":195,"passed_time":3.863907117,"remaining_time":15.84990471},
{"learn":[0.8527734825],"iteration":196,"passed_time":3.881496948,"remaining_time":15.82153325},
{"learn":[0.8523611355],"iteration":197,"passed_time":3.898791956,"remaining_time":15.79207651},
{"learn":[0.8519043268],"iteration":198,"passed_time":3.916668403,"remaining_time":15.76508237},
{"learn":[0.8514481513],"iteration":199,"passed_time":3.934876589,"remaining_time":15.73950635},
{"learn":[0.8510520353],"iteration":200,"passed_time":3.954496519,"remaining_time":15.71961552},
{"learn":[0.85056939],"iteration":201,"passed_time":3.973178397,"remaining_time":15.69602159},
{"learn":[0.8498152206],"iteration":202,"passed_time":3.992109726,"remaining_time":15.67345543},
{"learn":[0.8493654752],"iteration":203,"passed_time":4.009970964,"remaining_time":15.64674945},
{"learn":[0.8485502267],"iteration":204,"passed_time":4.028249773,"remaining_time":15.62174912},
{"learn":[0.8479997177],"iteration":205,"passed_time":4.045338954,"remaining_time":15.59222878},
{"learn":[0.8476239991],"iteration":206,"passed_time":4.06268346,"remaining_time":15.56380669},
{"learn":[0.8471200961],"iteration":207,"passed_time":4.07986518,"remaining_time":15.53487126},
{"learn":[0.8468308973],"iteration":208,"passed_time":4.097010109,"remaining_time":15.50590907},
{"learn":[0.8460956124],"iteration":209,"passed_time":4.114533151,"remaining_time":15.47848185},
{"learn":[0.845648835],"iteration":210,"passed_time":4.133372899,"remaining_time":15.45607212},
{"learn":[0.8450211255],"iteration":211,"passed_time":4.154263829,"remaining_time":15.44132027},
{"learn":[0.844572616],"iteration":212,"passed_time":4.18237506,"remaining_time":15.4531886},
{"learn":[0.8442254841],"iteration":213,"passed_time":4.199469241,"remaining_time":15.4242188},
{"learn":[0.843610236],"iteration":214,"passed_time":4.216743375,"remaining_time":15.39601651},
{"learn":[0.8431643622],"iteration":215,"passed_time":4.234684028,"remaining_time":15.37033462},
{"learn":[0.8426966478],"iteration":216,"passed_time":4.25259364,"remaining_time":15.34461207},
{"learn":[0.8421951194],"iteration":217,"passed_time":4.27000756,"remaining_time":15.31718308},
{"learn":[0.8416374345],"iteration":218,"passed_time":4.287310985,"remaining_time":15.2894515},
{"learn":[0.8413565714],"iteration":219,"passed_time":4.304323502,"remaining_time":15.26078332},
{"learn":[0.8408148582],"iteration":220,"passed_time":4.321779962,"remaining_time":15.23378548},
{"learn":[0.8402624837],"iteration":221,"passed_time":4.340065229,"remaining_time":15.20977814},
{"learn":[0.8394691897],"iteration":222,"passed_time":4.358681943,"remaining_time":15.18697699},
{"learn":[0.8391337594],"iteration":223,"passed_time":4.377988175,"remaining_time":15.16660189},
{"learn":[0.8386551226],"iteration":224,"passed_time":4.396468435,"remaining_time":15.14339128},
{"learn":[0.8382519845],"iteration":225,"passed_time":4.413512243,"remaining_time":15.11530299},
{"learn":[0.8377258747],"iteration":226,"passed_time":4.43112299,"remaining_time":15.08924261},
{"learn":[0.8372395898],"iteration":227,"passed_time":4.4491061,"remaining_time":15.06451715},
{"learn":[0.8368287912],"iteration":228,"passed_time":4.466235405,"remaining_time":15.03697597},
{"learn":[0.8365044457],"iteration":229,"passed_time":4.483154967,"remaining_time":15.00882315},
{"learn":[0.8360455101],"iteration":230,"passed_time":4.50029473,"remaining_time":14.98150064},
{"learn":[0.835561706],"iteration":231,"passed_time":4.517249499,"remaining_time":14.95365351},
{"learn":[0.8351940685],"iteration":232,"passed_time":4.534624004,"remaining_time":14.92728159},
{"learn":[0.8344894753],"iteration":233,"passed_time":4.553227718,"remaining_time":14.90501039},
{"learn":[0.8339067245],"iteration":234,"passed_time":4.573500877,"remaining_time":14.88820498},
{"learn":[0.8333789699],"iteration":235,"passed_time":4.592675364,"remaining_time":14.86781347},
{"learn":[0.8328987164],"iteration":236,"passed_time":4.610461688,"remaining_time":14.84296316},
{"learn":[0.8324077786],"iteration":237,"passed_time":4.627679199,"remaining_time":14.81635105},
{"learn":[0.831845324],"iteration":238,"passed_time":4.645448941,"remaining_time":14.79157592},
{"learn":[0.8314568038],"iteration":239,"passed_time":4.662229007,"remaining_time":14.76372519},
{"learn":[0.8308656076],"iteration":240,"passed_time":4.679817172,"remaining_time":14.73851134},
{"learn":[0.8305711387],"iteration":241,"passed_time":4.697085681,"remaining_time":14.71235928},
{"learn":[0.8301194528],"iteration":242,"passed_time":4.714220985,"remaining_time":14.68586537},
{"learn":[0.8296292364],"iteration":243,"passed_time":4.731455787,"remaining_time":14.65975645},
{"learn":[0.8292166823],"iteration":244,"passed_time":4.749147323,"remaining_time":14.63512746},
{"learn":[0.8287559624],"iteration":245,"passed_time":4.767732204,"remaining_time":14.61329302},
{"learn":[0.8283070817],"iteration":246,"passed_time":4.786704948,"remaining_time":14.59266731},
{"learn":[0.827950437],"iteration":247,"passed_time":4.805508447,"remaining_time":14.57154174},
{"learn":[0.8275200833],"iteration":248,"passed_time":4.823068863,"remaining_time":14.54668561},
{"learn":[0.8271882816],"iteration":249,"passed_time":4.840896228,"remaining_time":14.52268868},
{"learn":[0.8266257804],"iteration":250,"passed_time":4.859712018,"remaining_time":14.50169045},
{"learn":[0.8261983275],"iteration":251,"passed_time":4.877825707,"remaining_time":14.47862551},
{"learn":[0.8258865125],"iteration":252,"passed_time":4.896188929,"remaining_time":14.45633648},
{"learn":[0.8254012626],"iteration":253,"passed_time":4.914956388,"remaining_time":14.43526561},
{"learn":[0.8250300631],"iteration":254,"passed_time":4.932317727,"remaining_time":14.41010473},
{"learn":[0.8247127693],"iteration":255,"passed_time":4.94950203,"remaining_time":14.38449028},
{"learn":[0.8241730931],"iteration":256,"passed_time":4.967296646,"remaining_time":14.36070587},
{"learn":[0.8237846395],"iteration":257,"passed_time":4.985303214,"remaining_time":14.33757746},
{"learn":[0.8232228282],"iteration":258,"passed_time":5.004718359,"remaining_time":14.31851855},
{"learn":[0.8224881672],"iteration":259,"passed_time":5.025153012,"remaining_time":14.30235857},
{"learn":[0.8221390659],"iteration":260,"passed_time":5.043564316,"remaining_time":14.2804369},
{"learn":[0.8217136418],"iteration":261,"passed_time":5.061403348,"remaining_time":14.25693004},
{"learn":[0.821302372],"iteration":262,"passed_time":5.079315043,"remaining_time":14.23366991},
{"learn":[0.8209009102],"iteration":263,"passed_time":5.098162874,"remaining_time":14.21306013},
{"learn":[0.8202904619],"iteration":264,"passed_time":5.117100702,"remaining_time":14.19271327},
{"learn":[0.819995171],"iteration":265,"passed_time":5.135424093,"remaining_time":14.17068152},
{"learn":[0.8195934192],"iteration":266,"passed_time":5.154039515,"remaining_time":14.14947927},
{"learn":[0.8193188958],"iteration":267,"passed_time":5.171796924,"remaining_time":14.12595279},
{"learn":[0.8189799828],"iteration":268,"passed_time":5.190646213,"remaining_time":14.10543636},
{"learn":[0.8184092295],"iteration":269,"passed_time":5.209639623,"remaining_time":14.08532194},
{"learn":[0.8181396184],"iteration":270,"passed_time":5.230487637,"remaining_time":14.07020475},
{"learn":[0.8176220126],"iteration":271,"passed_time":5.249612501,"remaining_time":14.05043346},
{"learn":[0.8173242814],"iteration":272,"passed_time":5.268347502,"remaining_time":14.0296287},
{"learn":[0.8169164432],"iteration":273,"passed_time":5.286733307,"remaining_time":14.0079138},
{"learn":[0.8163706434],"iteration":274,"passed_time":5.306724392,"remaining_time":13.99045521},
{"learn":[0.8160853438],"iteration":275,"passed_time":5.324879163,"remaining_time":13.96816128},
{"learn":[0.8157334491],"iteration":276,"passed_time":5.342371247,"remaining_time":13.94416755},
{"learn":[0.8151015085],"iteration":277,"passed_time":5.360927546,"remaining_time":13.92298449},
{"learn":[0.8146127752],"iteration":278,"passed_time":5.378575709,"remaining_time":13.89947343},
{"learn":[0.8142393031],"iteration":279,"passed_time":5.396310494,"remaining_time":13.87622698},
{"learn":[0.8139393932],"iteration":280,"passed_time":5.413990155,"remaining_time":13.85287872},
{"learn":[0.8135929884],"iteration":281,"passed_time":5.433613836,"remaining_time":13.83452033},
{"learn":[0.813276911],"iteration":282,"passed_time":5.452619828,"remaining_time":13.81458804},
{"learn":[0.8128683752],"iteration":283,"passed_time":5.469916336,"remaining_time":13.79035245},
{"learn":[0.8124193676],"iteration":284,"passed_time":5.487728201,"remaining_time":13.76745847},
{"learn":[0.8120644944],"iteration":285,"passed_time":5.50523016,"remaining_time":13.74382634},
{"learn":[0.8116553714],"iteration":286,"passed_time":5.522664039,"remaining_time":13.7200678},
{"learn":[0.8112534858],"iteration":287,"passed_time":5.540259495,"remaining_time":13.69675264},
{"learn":[0.8108248641],"iteration":288,"passed_time":5.558910832,"remaining_time":13.67607475},
{"learn":[0.8105329755],"iteration":289,"passed_time":5.576847485,"remaining_time":13.65366108},
{"learn":[0.8101163082],"iteration":290,"passed_time":5.595282039,"remaining_time":13.63249129},
{"learn":[0.8098727767],"iteration":291,"passed_time":5.613444517,"remaining_time":13.61068054},
{"learn":[0.8094071334],"iteration":292,"passed_time":5.63345031,"remaining_time":13.59334256},
{"learn":[0.8091537627],"iteration":293,"passed_time":5.653636971,"remaining_time":13.57642075},
{"learn":[0.8089137745],"iteration":294,"passed_time":5.673593266,"remaining_time":13.55892628},
{"learn":[0.8086546083],"iteration":295,"passed_time":5.69147717,"remaining_time":13.53648624},
{"learn":[0.8081754965],"iteration":296,"passed_time":5.710054594,"remaining_time":13.51571845},
{"learn":[0.8079270141],"iteration":297,"passed_time":5.728774846,"remaining_time":13.49530182},
{"learn":[0.8077173159],"iteration":298,"passed_time":5.747484848,"remaining_time":13.4748725},
{"learn":[0.8073390297],"iteration":299,"passed_time":5.76665821,"remaining_time":13.45553582},
{"learn":[0.8070105791],"iteration":300,"passed_time":5.784872937,"remaining_time":13.43397403},
{"learn":[0.8066815942],"iteration":301,"passed_time":5.802305982,"remaining_time":13.41062773},
{"learn":[0.8062507726],"iteration":302,"passed_time":5.82066258,"remaining_time":13.38944494},
{"learn":[0.805798379],"iteration":303,"passed_time":5.838775727,"remaining_time":13.36772337},
{"learn":[0.8054126376],"iteration":304,"passed_time":5.858554485,"remaining_time":13.34982088},
{"learn":[0.8050647611],"iteration":305,"passed_time":5.877107159,"remaining_time":13.32912539},
{"learn":[0.8045899771],"iteration":306,"passed_time":5.896065195,"remaining_time":13.30935889},
{"learn":[0.8042425131],"iteration":307,"passed_time":5.916122069,"remaining_time":13.29206647},
{"learn":[0.8038724755],"iteration":308,"passed_time":5.937394486,"remaining_time":13.2774744},
{"learn":[0.8033358109],"iteration":309,"passed_time":5.958683944,"remaining_time":13.26287717},
{"learn":[0.8031977012],"iteration":310,"passed_time":5.979563041,"remaining_time":13.24732777},
{"learn":[0.8028375761],"iteration":311,"passed_time":6.000511844,"remaining_time":13.23189791},
{"learn":[0.8025106751],"iteration":312,"passed_time":6.020400682,"remaining_time":13.21410629},
{"learn":[0.8022457162],"iteration":313,"passed_time":6.041241572,"remaining_time":13.19838127},
{"learn":[0.8019461609],"iteration":314,"passed_time":6.062172584,"remaining_time":13.18281975},
{"learn":[0.801578938],"iteration":315,"passed_time":6.083492791,"remaining_time":13.16806667},
{"learn":[0.8011833813],"iteration":316,"passed_time":6.104948118,"remaining_time":13.1535633},
{"learn":[0.8008725296],"iteration":317,"passed_time":6.125152238,"remaining_time":13.13633279},
{"learn":[0.8003848393],"iteration":318,"passed_time":6.145802301,"remaining_time":13.12003563},
{"learn":[0.7998992366],"iteration":319,"passed_time":6.165583226,"remaining_time":13.10186435},
{"learn":[0.7996752219],"iteration":320,"passed_time":6.185576727,"remaining_time":13.0841327},
{"learn":[0.7993141338],"iteration":321,"passed_time":6.205299112,"remaining_time":13.06581614},
{"learn":[0.7989672634],"iteration":322,"passed_time":6.224259106,"remaining_time":13.04589293},
{"learn":[0.7986310823],"iteration":323,"passed_time":6.243378511,"remaining_time":13.02630825},
{"learn":[0.7983490812],"iteration":324,"passed_time":6.265238867,"remaining_time":13.01241919},
{"learn":[0.7976658172],"iteration":325,"passed_time":6.286764151,"remaining_time":12.99778846},
{"learn":[0.7973109255],"iteration":326,"passed_time":6.306324458,"remaining_time":12.97907144},
{"learn":[0.7967395605],"iteration":327,"passed_time":6.32564219,"remaining_time":12.95985229},
{"learn":[0.7961139519],"iteration":328,"passed_time":6.346250838,"remaining_time":12.94326539},
{"learn":[0.7958860014],"iteration":329,"passed_time":6.366248756,"remaining_time":12.92541414},
{"learn":[0.7954286891],"iteration":330,"passed_time":6.385941475,"remaining_time":12.90693307},
{"learn":[0.7951192239],"iteration":331,"passed_time":6.40588652,"remaining_time":12.8889524},
{"learn":[0.794516036],"iteration":332,"passed_time":6.424560148,"remaining_time":12.86841327},
{"learn":[0.7941622542],"iteration":333,"passed_time":6.4435581,"remaining_time":12.84853202},
{"learn":[0.7940019676],"iteration":334,"passed_time":6.463287401,"remaining_time":12.83010783},
{"learn":[0.793621032],"iteration":335,"passed_time":6.484262328,"remaining_time":12.81413746},
{"learn":[0.7933463787],"iteration":336,"passed_time":6.505145508,"remaining_time":12.79795689},
{"learn":[0.7929793846],"iteration":337,"passed_time":6.523463274,"remaining_time":12.77672393},
{"learn":[0.7927223772],"iteration":338,"passed_time":6.540924734,"remaining_time":12.75383849},
{"learn":[0.7921131775],"iteration":339,"passed_time":6.558627187,"remaining_time":12.73145277},
{"learn":[0.7916917563],"iteration":340,"passed_time":6.575817198,"remaining_time":12.7081042},
{"learn":[0.7914051676],"iteration":341,"passed_time":6.595530417,"remaining_time":12.68964624},
{"learn":[0.7911226387],"iteration":342,"passed_time":6.613490611,"remaining_time":12.66782312},
{"learn":[0.7908751615],"iteration":343,"passed_time":6.633623899,"remaining_time":12.65016651},
{"learn":[0.790616093],"iteration":344,"passed_time":6.65297588,"remaining_time":12.63101218},
{"learn":[0.7903344988],"iteration":345,"passed_time":6.672412983,"remaining_time":12.6120176},
{"learn":[0.7898995303],"iteration":346,"passed_time":6.694016723,"remaining_time":12.59709775},
{"learn":[0.7896188868],"iteration":347,"passed_time":6.711856462,"remaining_time":12.57508739},
{"learn":[0.7891132748],"iteration":348,"passed_time":6.729313506,"remaining_time":12.55238708},
{"learn":[0.7886542036],"iteration":349,"passed_time":6.748022759,"remaining_time":12.53204227},
{"learn":[0.7884503679],"iteration":350,"passed_time":6.766253235,"remaining_time":12.51082151},
{"learn":[0.7882439663],"iteration":351,"passed_time":6.785518427,"remaining_time":12.49152256},
{"learn":[0.7878197218],"iteration":352,"passed_time":6.804671248,"remaining_time":12.47201784},
{"learn":[0.7875224431],"iteration":353,"passed_time":6.823421708,"remaining_time":12.45178086},
{"learn":[0.7872176629],"iteration":354,"passed_time":6.843530497,"remaining_time":12.4340202},
{"learn":[0.7869434064],"iteration":355,"passed_time":6.864235433,"remaining_time":12.41732477},
{"learn":[0.7866011231],"iteration":356,"passed_time":6.88380799,"remaining_time":12.39856733},
{"learn":[0.7861072829],"iteration":357,"passed_time":6.90373291,"remaining_time":12.38043723},
{"learn":[0.7857957174],"iteration":358,"passed_time":6.924215062,"remaining_time":12.36329207},
{"learn":[0.7855207032],"iteration":359,"passed_time":6.943538127,"remaining_time":12.34406778},
{"learn":[0.7852119621],"iteration":360,"passed_time":6.963756954,"remaining_time":12.32642851},
{"learn":[0.7849607766],"iteration":361,"passed_time":6.983363218,"remaining_time":12.3076954},
{"learn":[0.7846116815],"iteration":362,"passed_time":7.00312981,"remaining_time":12.28923881},
{"learn":[0.784275576],"iteration":363,"passed_time":7.023060647,"remaining_time":12.27106201},
{"learn":[0.7840343451],"iteration":364,"passed_time":7.043621796,"remaining_time":12.25397217},
{"learn":[0.7836699467],"iteration":365,"passed_time":7.0642704,"remaining_time":12.23701485},
{"learn":[0.7832627196],"iteration":366,"passed_time":7.084165363,"remaining_time":12.21873753},
{"learn":[0.7829361267],"iteration":367,"passed_time":7.107172264,"remaining_time":12.20579585},
{"learn":[0.782606889],"iteration":368,"passed_time":7.126434457,"remaining_time":12.18639605},
{"learn":[0.7822871948],"iteration":369,"passed_time":7.146236089,"remaining_time":12.1679155},
{"learn":[0.7820101266],"iteration":370,"passed_time":7.165992432,"remaining_time":12.14935105},
{"learn":[0.7818113647],"iteration":371,"passed_time":7.184307447,"remaining_time":12.12834698},
{"learn":[0.7815320137],"iteration":372,"passed_time":7.202510467,"remaining_time":12.10716907},
{"learn":[0.7812944136],"iteration":373,"passed_time":7.220937228,"remaining_time":12.08638156},
{"learn":[0.781082224],"iteration":374,"passed_time":7.2398126,"remaining_time":12.06635433},
{"learn":[0.7807742221],"iteration":375,"passed_time":7.26028321,"remaining_time":12.04898065},
{"learn":[0.7805597782],"iteration":376,"passed_time":7.28007751,"remaining_time":12.03047291},
{"learn":[0.7804020919],"iteration":377,"passed_time":7.300899609,"remaining_time":12.01364962},
{"learn":[0.7800327639],"iteration":378,"passed_time":7.321904826,"remaining_time":11.99710527},
{"learn":[0.7797437985],"iteration":379,"passed_time":7.340302672,"remaining_time":11.97628331},
{"learn":[0.7794294273],"iteration":380,"passed_time":7.359177919,"remaining_time":11.95624969},
{"learn":[0.7791670057],"iteration":381,"passed_time":7.378067666,"remaining_time":11.9362456},
{"learn":[0.7789076452],"iteration":382,"passed_time":7.396923996,"remaining_time":11.91619349},
{"learn":[0.7784812091],"iteration":383,"passed_time":7.416318309,"remaining_time":11.89701062},
{"learn":[0.777973436],"iteration":384,"passed_time":7.435175098,"remaining_time":11.87696801},
{"learn":[0.7775991651],"iteration":385,"passed_time":7.455068311,"remaining_time":11.85858016},
{"learn":[0.7773854117],"iteration":386,"passed_time":7.474149343,"remaining_time":11.83889805},
{"learn":[0.7771414866],"iteration":387,"passed_time":7.494069055,"remaining_time":11.82054191},
{"learn":[0.7768863288],"iteration":388,"passed_time":7.525059565,"remaining_time":11.81956657},
{"learn":[0.7764432387],"iteration":389,"passed_time":7.547441404,"remaining_time":11.80497245},
{"learn":[0.7761041815],"iteration":390,"passed_time":7.566435897,"remaining_time":11.78506256},
{"learn":[0.7759558236],"iteration":391,"passed_time":7.58527902,"remaining_time":11.76492256},
{"learn":[0.775515232],"iteration":392,"passed_time":7.605287479,"remaining_time":11.74658906},
{"learn":[0.7752244068],"iteration":393,"passed_time":7.624737998,"remaining_time":11.7273889},
{"learn":[0.7748917266],"iteration":394,"passed_time":7.644936618,"remaining_time":11.7093333},
{"learn":[0.774398669],"iteration":395,"passed_time":7.664063148,"remaining_time":11.68963167},
{"learn":[0.7741238554],"iteration":396,"passed_time":7.682733318,"remaining_time":11.66923978},
{"learn":[0.7737342556],"iteration":397,"passed_time":7.701922929,"remaining_time":11.64964222},
{"learn":[0.7733418559],"iteration":398,"passed_time":7.721003086,"remaining_time":11.62988184},
{"learn":[0.7729984424],"iteration":399,"passed_time":7.746602151,"remaining_time":11.61990323},
{"learn":[0.7726174031],"iteration":400,"passed_time":7.804228441,"remaining_time":11.65768787},
{"learn":[0.7722746494],"iteration":401,"passed_time":7.828295765,"remaining_time":11.64507679},
{"learn":[0.7719975998],"iteration":402,"passed_time":7.848461136,"remaining_time":11.62662853},
{"learn":[0.7716838086],"iteration":403,"passed_time":7.866389331,"remaining_time":11.60487139},
{"learn":[0.7711134335],"iteration":404,"passed_time":7.886133215,"remaining_time":11.58580065},
{"learn":[0.7708614077],"iteration":405,"passed_time":7.904496938,"remaining_time":11.56470734},
{"learn":[0.7705527675],"iteration":406,"passed_time":7.921856277,"remaining_time":11.54216406},
{"learn":[0.77026713],"iteration":407,"passed_time":7.941083595,"remaining_time":11.52235659},
{"learn":[0.7699970093],"iteration":408,"passed_time":7.958676426,"remaining_time":11.50019014},
{"learn":[0.7698398465],"iteration":409,"passed_time":7.97652829,"remaining_time":11.47841876},
{"learn":[0.7696729857],"iteration":410,"passed_time":7.993878338,"remaining_time":11.4559473},
{"learn":[0.7694757183],"iteration":411,"passed_time":8.01134084,"remaining_time":11.4336612},
{"learn":[0.7692260275],"iteration":412,"passed_time":8.028347316,"remaining_time":11.4107503},
{"learn":[0.7689920838],"iteration":413,"passed_time":8.046035186,"remaining_time":11.38883241},
{"learn":[0.7687101215],"iteration":414,"passed_time":8.065372667,"remaining_time":11.36926027},
{"learn":[0.7684727822],"iteration":415,"passed_time":8.089349952,"remaining_time":11.35620282},
{"learn":[0.7680750696],"iteration":416,"passed_time":8.116741791,"remaining_time":11.34786682},
{"learn":[0.7678410989],"iteration":417,"passed_time":8.145002934,"remaining_time":11.34065002},
{"learn":[0.7676654096],"iteration":418,"passed_time":8.174231461,"remaining_time":11.33467417},
{"learn":[0.7674781412],"iteration":419,"passed_time":8.198406281,"remaining_time":11.32160867},
{"learn":[0.7671863581],"iteration":420,"passed_time":8.224507246,"remaining_time":11.31113942},
{"learn":[0.7668829507],"iteration":421,"passed_time":8.261726257,"remaining_time":11.31582412},
{"learn":[0.7667134313],"iteration":422,"passed_time":8.283618154,"remaining_time":11.29940349},
{"learn":[0.7664816243],"iteration":423,"passed_time":8.305861539,"remaining_time":11.28343454},
{"learn":[0.7662447171],"iteration":424,"passed_time":8.3285442,"remaining_time":11.26803039},
{"learn":[0.7658831467],"iteration":425,"passed_time":8.358209171,"remaining_time":11.26200015},
{"learn":[0.7656547899],"iteration":426,"passed_time":8.380869542,"remaining_time":11.2464596},
{"learn":[0.7653790163],"iteration":427,"passed_time":8.407286871,"remaining_time":11.23590675},
{"learn":[0.7649307632],"iteration":428,"passed_time":8.429016315,"remaining_time":11.21904036},
{"learn":[0.7647320187],"iteration":429,"passed_time":8.451015291,"remaining_time":11.20250864},
{"learn":[0.7645449556],"iteration":430,"passed_time":8.472544825,"remaining_time":11.1853318},
{"learn":[0.7642922441],"iteration":431,"passed_time":8.494290601,"remaining_time":11.16841912},
{"learn":[0.7640675762],"iteration":432,"passed_time":8.514622341,"remaining_time":11.14963249},
{"learn":[0.7638325563],"iteration":433,"passed_time":8.539451306,"remaining_time":11.13670378},
{"learn":[0.7634356747],"iteration":434,"passed_time":8.561479865,"remaining_time":11.12008304},
{"learn":[0.7632404525],"iteration":435,"passed_time":8.584484599,"remaining_time":11.10470026},
{"learn":[0.7630484192],"iteration":436,"passed_time":8.607761033,"remaining_time":11.08963264},
{"learn":[0.7628259562],"iteration":437,"passed_time":8.633016109,"remaining_time":11.07706633},
{"learn":[0.7626234937],"iteration":438,"passed_time":8.652902114,"remaining_time":11.05758106},
{"learn":[0.7623810209],"iteration":439,"passed_time":8.670150707,"remaining_time":11.03473726},
{"learn":[0.7619851203],"iteration":440,"passed_time":8.688175982,"remaining_time":11.01290334},
{"learn":[0.7616864702],"iteration":441,"passed_time":8.707838661,"remaining_time":10.99315378},
{"learn":[0.7614091526],"iteration":442,"passed_time":8.728038988,"remaining_time":10.97408062},
{"learn":[0.7611319749],"iteration":443,"passed_time":8.749396778,"remaining_time":10.95645182},
{"learn":[0.7608747508],"iteration":444,"passed_time":8.770786232,"remaining_time":10.93884575},
{"learn":[0.7606335556],"iteration":445,"passed_time":8.790090465,"remaining_time":10.91863255},
{"learn":[0.7604017878],"iteration":446,"passed_time":8.809287285,"remaining_time":10.89829053},
{"learn":[0.7601931887],"iteration":447,"passed_time":8.827752253,"remaining_time":10.87705188},
{"learn":[0.7598651428],"iteration":448,"passed_time":8.84984506,"remaining_time":10.86027757},
{"learn":[0.759544574],"iteration":449,"passed_time":8.883214533,"remaining_time":10.85726221},
{"learn":[0.7593883301],"iteration":450,"passed_time":8.907067197,"remaining_time":10.84252747},
{"learn":[0.7591792359],"iteration":451,"passed_time":8.936493801,"remaining_time":10.83451018},
{"learn":[0.7589432174],"iteration":452,"passed_time":8.969896439,"remaining_time":10.83119945},
{"learn":[0.7586865097],"iteration":453,"passed_time":8.997635725,"remaining_time":10.82094517},
{"learn":[0.7584704448],"iteration":454,"passed_time":9.030747956,"remaining_time":10.81704975},
{"learn":[0.7582730453],"iteration":455,"passed_time":9.04860357,"remaining_time":10.79482531},
{"learn":[0.7580796132],"iteration":456,"passed_time":9.065641461,"remaining_time":10.77164839},
{"learn":[0.7578517301],"iteration":457,"passed_time":9.083126129,"remaining_time":10.74902699},
{"learn":[0.7576439874],"iteration":458,"passed_time":9.100217727,"remaining_time":10.72596469},
{"learn":[0.7574022193],"iteration":459,"passed_time":9.117614523,"remaining_time":10.70328661},
{"learn":[0.7570644392],"iteration":460,"passed_time":9.135822667,"remaining_time":10.68158008},
{"learn":[0.7568108059],"iteration":461,"passed_time":9.154576877,"remaining_time":10.66052459},
{"learn":[0.7564653694],"iteration":462,"passed_time":9.173890775,"remaining_time":10.64012818},
{"learn":[0.7562644212],"iteration":463,"passed_time":9.192690816,"remaining_time":10.61914284},
{"learn":[0.7560652651],"iteration":464,"passed_time":9.211919802,"remaining_time":10.59866042},
{"learn":[0.7558956881],"iteration":465,"passed_time":9.230055198,"remaining_time":10.57693021},
{"learn":[0.7556344373],"iteration":466,"passed_time":9.249194228,"remaining_time":10.55636086},
{"learn":[0.7552746719],"iteration":467,"passed_time":9.267196879,"remaining_time":10.53450585},
{"learn":[0.7550494551],"iteration":468,"passed_time":9.285524394,"remaining_time":10.51303508},
{"learn":[0.7549032386],"iteration":469,"passed_time":9.303056935,"remaining_time":10.49068122},
{"learn":[0.7546015554],"iteration":470,"passed_time":9.321964348,"remaining_time":10.46989202},
{"learn":[0.7543147694],"iteration":471,"passed_time":9.342037888,"remaining_time":10.45041526},
{"learn":[0.7540850759],"iteration":472,"passed_time":9.361507532,"remaining_time":10.43026315},
{"learn":[0.7540028147],"iteration":473,"passed_time":9.384034157,"remaining_time":10.41350626},
{"learn":[0.7537686739],"iteration":474,"passed_time":9.407896404,"remaining_time":10.39820129},
{"learn":[0.7535718763],"iteration":475,"passed_time":9.432462295,"remaining_time":10.38363496},
{"learn":[0.753269018],"iteration":476,"passed_time":9.452688455,"remaining_time":10.36426847},
{"learn":[0.7529519801],"iteration":477,"passed_time":9.471945065,"remaining_time":10.34383959},
{"learn":[0.7525473303],"iteration":478,"passed_time":9.490887017,"remaining_time":10.32307335},
{"learn":[0.7522822589],"iteration":479,"passed_time":9.511056263,"remaining_time":10.30364428},
{"learn":[0.7520505721],"iteration":480,"passed_time":9.5304862,"remaining_time":10.28341442},
{"learn":[0.7519012377],"iteration":481,"passed_time":9.549308073,"remaining_time":10.2625344},
{"learn":[0.7515986651],"iteration":482,"passed_time":9.56867897,"remaining_time":10.24225057},
{"learn":[0.7514755634],"iteration":483,"passed_time":9.588086699,"remaining_time":10.22200979},
{"learn":[0.7512320687],"iteration":484,"passed_time":9.607249853,"remaining_time":10.20151273},
{"learn":[0.751017582],"iteration":485,"passed_time":9.629155416,"remaining_time":10.18392157},
{"learn":[0.7507894984],"iteration":486,"passed_time":9.649578153,"remaining_time":10.1647507},
{"learn":[0.7506053363],"iteration":487,"passed_time":9.669136835,"remaining_time":10.14466816},
{"learn":[0.7502788538],"iteration":488,"passed_time":9.688436026,"remaining_time":10.12431658},
{"learn":[0.7500758373],"iteration":489,"passed_time":9.706635379,"remaining_time":10.10282458},
{"learn":[0.7496075744],"iteration":490,"passed_time":9.726118481,"remaining_time":10.0826768},
{"learn":[0.7491594516],"iteration":491,"passed_time":9.745860324,"remaining_time":10.06279887},
{"learn":[0.7489171148],"iteration":492,"passed_time":9.764171048,"remaining_time":10.04144974},
{"learn":[0.7486597271],"iteration":493,"passed_time":9.783445031,"remaining_time":10.02109957},
{"learn":[0.7483466038],"iteration":494,"passed_time":9.802521646,"remaining_time":10.00055239},
{"learn":[0.7480997709],"iteration":495,"passed_time":9.823773356,"remaining_time":9.982221313},
{"learn":[0.7478750097],"iteration":496,"passed_time":9.844832988,"remaining_time":9.963684091},
{"learn":[0.7477261105],"iteration":497,"passed_time":9.864647787,"remaining_time":9.943881906},
{"learn":[0.7473946462],"iteration":498,"passed_time":9.883839148,"remaining_time":9.923453734},
{"learn":[0.747205067],"iteration":499,"passed_time":9.902952012,"remaining_time":9.902952012},
{"learn":[0.7469536809],"iteration":500,"passed_time":9.921473479,"remaining_time":9.881866799},
{"learn":[0.7466619451],"iteration":501,"passed_time":9.940864417,"remaining_time":9.861654342},
{"learn":[0.7464487477],"iteration":502,"passed_time":9.960926083,"remaining_time":9.842107879},
{"learn":[0.7461800689],"iteration":503,"passed_time":9.980808713,"remaining_time":9.822383178},
{"learn":[0.7459962212],"iteration":504,"passed_time":9.999780915,"remaining_time":9.801765451},
{"learn":[0.7457364369],"iteration":505,"passed_time":10.0186235,"remaining_time":9.781027682},
{"learn":[0.7453049538],"iteration":506,"passed_time":10.03889795,"remaining_time":9.761689719},
{"learn":[0.7450500187],"iteration":507,"passed_time":10.0591771,"remaining_time":9.742352629},
{"learn":[0.7448488357],"iteration":508,"passed_time":10.07739104,"remaining_time":9.721019648},
{"learn":[0.7446620465],"iteration":509,"passed_time":10.09575301,"remaining_time":9.69984113},
{"learn":[0.7444324069],"iteration":510,"passed_time":10.11430931,"remaining_time":9.678859596},
{"learn":[0.7440611704],"iteration":511,"passed_time":10.13356688,"remaining_time":9.658555932},
{"learn":[0.7438885647],"iteration":512,"passed_time":10.15548265,"remaining_time":9.640779825},
{"learn":[0.7436596001],"iteration":513,"passed_time":10.1777112,"remaining_time":9.623283354},
{"learn":[0.743328189],"iteration":514,"passed_time":10.19904782,"remaining_time":9.604928534},
{"learn":[0.7430001213],"iteration":515,"passed_time":10.22110463,"remaining_time":9.587237678},
{"learn":[0.742756394],"iteration":516,"passed_time":10.24320919,"remaining_time":9.569574542},
{"learn":[0.7426245459],"iteration":517,"passed_time":10.26711881,"remaining_time":9.553573873},
{"learn":[0.7423439932],"iteration":518,"passed_time":10.28649225,"remaining_time":9.533338673},
{"learn":[0.7420696009],"iteration":519,"passed_time":10.30571457,"remaining_time":9.512967292},
{"learn":[0.741873516],"iteration":520,"passed_time":10.32366397,"remaining_time":9.491430022},
{"learn":[0.7416422395],"iteration":521,"passed_time":10.34151463,"remaining_time":9.469816074},
{"learn":[0.7415085634],"iteration":522,"passed_time":10.35857727,"remaining_time":9.447497812},
{"learn":[0.7411261713],"iteration":523,"passed_time":10.37628126,"remaining_time":9.425782213},
{"learn":[0.7408509409],"iteration":524,"passed_time":10.39466906,"remaining_time":9.404700582},
{"learn":[0.7406264184],"iteration":525,"passed_time":10.41242014,"remaining_time":9.383055412},
{"learn":[0.7404466958],"iteration":526,"passed_time":10.43060562,"remaining_time":9.36181491},
{"learn":[0.740218329],"iteration":527,"passed_time":10.44892847,"remaining_time":9.340708781},
{"learn":[0.7399500787],"iteration":528,"passed_time":10.46941499,"remaining_time":9.321539626},
{"learn":[0.7398380823],"iteration":529,"passed_time":10.48818133,"remaining_time":9.300840045},
{"learn":[0.7395735052],"iteration":530,"passed_time":10.50735252,"remaining_time":9.280505336},
{"learn":[0.7391749941],"iteration":531,"passed_time":10.52638831,"remaining_time":9.260055878},
{"learn":[0.73901079],"iteration":532,"passed_time":10.54619073,"remaining_time":9.240283435},
{"learn":[0.73870766],"iteration":533,"passed_time":10.56578337,"remaining_time":9.22032781},
{"learn":[0.7385206182],"iteration":534,"passed_time":10.58549021,"remaining_time":9.200472803},
{"learn":[0.7383708165],"iteration":535,"passed_time":10.60693171,"remaining_time":9.182119987},
{"learn":[0.7381151696],"iteration":536,"passed_time":10.62749365,"remaining_time":9.162997318},
{"learn":[0.7379699911],"iteration":537,"passed_time":10.64857857,"remaining_time":9.144318403},
{"learn":[0.7377948627],"iteration":538,"passed_time":10.670879,"remaining_time":9.126670163},
{"learn":[0.7375752413],"iteration":539,"passed_time":10.69040414,"remaining_time":9.106640563},
{"learn":[0.7373582785],"iteration":540,"passed_time":10.70799893,"remaining_time":9.084975061},
{"learn":[0.7371347903],"iteration":541,"passed_time":10.7260492,"remaining_time":9.063709474},
{"learn":[0.736932749],"iteration":542,"passed_time":10.74382061,"remaining_time":9.04222103},
{"learn":[0.7367526811],"iteration":543,"passed_time":10.76092633,"remaining_time":9.02018825},
{"learn":[0.7365950165],"iteration":544,"passed_time":10.77820901,"remaining_time":8.998321282},
{"learn":[0.7363151652],"iteration":545,"passed_time":10.79637224,"remaining_time":8.977203289},
{"learn":[0.7361364128],"iteration":546,"passed_time":10.81388999,"remaining_time":8.955561544},
{"learn":[0.7359664883],"iteration":547,"passed_time":10.83140245,"remaining_time":8.933930485},
{"learn":[0.7357107932],"iteration":548,"passed_time":10.84971875,"remaining_time":8.912974787},
{"learn":[0.7354793175],"iteration":549,"passed_time":10.86837476,"remaining_time":8.89230662},
{"learn":[0.7352360942],"iteration":550,"passed_time":10.88829847,"remaining_time":8.872678789},
{"learn":[0.7350778925],"iteration":551,"passed_time":10.9058538,"remaining_time":8.851127724},
{"learn":[0.7348637825],"iteration":552,"passed_time":10.92328089,"remaining_time":8.829487445},
{"learn":[0.7346004313],"iteration":553,"passed_time":10.94084126,"remaining_time":8.807969681},
{"learn":[0.734411986],"iteration":554,"passed_time":10.95794274,"remaining_time":8.786098229},
{"learn":[0.7340425904],"iteration":555,"passed_time":10.97598201,"remaining_time":8.764992828},
{"learn":[0.7337971461],"iteration":556,"passed_time":10.99352997,"remaining_time":8.743507676},
{"learn":[0.7336641875],"iteration":557,"passed_time":11.01093951,"remaining_time":8.721926998},
{"learn":[0.7335051532],"iteration":558,"passed_time":11.02836039,"remaining_time":8.700370184},
{"learn":[0.7332348732],"iteration":559,"passed_time":11.04549615,"remaining_time":8.678604122},
{"learn":[0.7330594683],"iteration":560,"passed_time":11.06313407,"remaining_time":8.657247515},
{"learn":[0.7328003898],"iteration":561,"passed_time":11.08369155,"remaining_time":8.638179536},
{"learn":[0.7326305084],"iteration":562,"passed_time":11.10189232,"remaining_time":8.617276987},
{"learn":[0.7324690721],"iteration":563,"passed_time":11.11958469,"remaining_time":8.595991001},
{"learn":[0.7321450597],"iteration":564,"passed_time":11.13696069,"remaining_time":8.574474163},
{"learn":[0.7319208168],"iteration":565,"passed_time":11.15445265,"remaining_time":8.553060869},
{"learn":[0.7317182429],"iteration":566,"passed_time":11.17176708,"remaining_time":8.531525828},
{"learn":[0.7314543443],"iteration":567,"passed_time":11.18925466,"remaining_time":8.510137349},
{"learn":[0.7311552563],"iteration":568,"passed_time":11.20680637,"remaining_time":8.488811152},
{"learn":[0.7307964578],"iteration":569,"passed_time":11.22459344,"remaining_time":8.467675756},
{"learn":[0.730470739],"iteration":570,"passed_time":11.2419267,"remaining_time":8.446211129},
{"learn":[0.7302746312],"iteration":571,"passed_time":11.25956407,"remaining_time":8.424988502},
{"learn":[0.7300804718],"iteration":572,"passed_time":11.27876185,"remaining_time":8.404941204},
{"learn":[0.7299389918],"iteration":573,"passed_time":11.29947604,"remaining_time":8.386022284},
{"learn":[0.7296507921],"iteration":574,"passed_time":11.31812808,"remaining_time":8.36557293},
{"learn":[0.7295182327],"iteration":575,"passed_time":11.33677967,"remaining_time":8.345129479},
{"learn":[0.7293461464],"iteration":576,"passed_time":11.35410451,"remaining_time":8.323719597},
{"learn":[0.7292045025],"iteration":577,"passed_time":11.37141135,"remaining_time":8.302310709},
{"learn":[0.7289808004],"iteration":578,"passed_time":11.38858524,"remaining_time":8.280819317},
{"learn":[0.7288095306],"iteration":579,"passed_time":11.40688488,"remaining_time":8.260158015},
{"learn":[0.7286872983],"iteration":580,"passed_time":11.42435334,"remaining_time":8.238905419},
{"learn":[0.728326987],"iteration":581,"passed_time":11.44231428,"remaining_time":8.218019536},
{"learn":[0.7281569402],"iteration":582,"passed_time":11.45990528,"remaining_time":8.196879077},
{"learn":[0.7278381855],"iteration":583,"passed_time":11.47733812,"remaining_time":8.17563811},
{"learn":[0.727644626],"iteration":584,"passed_time":11.49588479,"remaining_time":8.155200322},
{"learn":[0.7274997456],"iteration":585,"passed_time":11.51567634,"remaining_time":8.135648473},
{"learn":[0.7272737062],"iteration":586,"passed_time":11.53317272,"remaining_time":8.114480974},
{"learn":[0.7270858802],"iteration":587,"passed_time":11.55035135,"remaining_time":8.093103329},
{"learn":[0.726906642],"iteration":588,"passed_time":11.56744608,"remaining_time":8.071681388},
{"learn":[0.72668592],"iteration":589,"passed_time":11.58488295,"remaining_time":8.050511883},
{"learn":[0.7264993038],"iteration":590,"passed_time":11.60262099,"remaining_time":8.029563425},
{"learn":[0.7262656969],"iteration":591,"passed_time":11.61998933,"remaining_time":8.008371023},
{"learn":[0.7261090626],"iteration":592,"passed_time":11.63759537,"remaining_time":7.987354661},
{"learn":[0.7258033604],"iteration":593,"passed_time":11.65509991,"remaining_time":7.966280409},
{"learn":[0.725575024],"iteration":594,"passed_time":11.67314035,"remaining_time":7.945582927},
{"learn":[0.725344169],"iteration":595,"passed_time":11.69085976,"remaining_time":7.92467675},
{"learn":[0.7251933091],"iteration":596,"passed_time":11.70915082,"remaining_time":7.904167135},
{"learn":[0.7250250273],"iteration":597,"passed_time":11.728762,"remaining_time":7.884552381},
{"learn":[0.7248219375],"iteration":598,"passed_time":11.7557281,"remaining_time":7.869861384},
{"learn":[0.7246455101],"iteration":599,"passed_time":11.77313252,"remaining_time":7.848755015},
{"learn":[0.7243689519],"iteration":600,"passed_time":11.79083268,"remaining_time":7.827857306},
{"learn":[0.7241213077],"iteration":601,"passed_time":11.80841939,"remaining_time":7.806895211},
{"learn":[0.7239531758],"iteration":602,"passed_time":11.82559061,"remaining_time":7.785670766},
{"learn":[0.7238110837],"iteration":603,"passed_time":11.8430239,"remaining_time":7.764631567},
{"learn":[0.7234517755],"iteration":604,"passed_time":11.86035562,"remaining_time":7.743537967},
{"learn":[0.7233484812],"iteration":605,"passed_time":11.87737401,"remaining_time":7.72225307},
{"learn":[0.7232381652],"iteration":606,"passed_time":11.89506067,"remaining_time":7.7014149},
{"learn":[0.7230095995],"iteration":607,"passed_time":11.91246801,"remaining_time":7.680407007},
{"learn":[0.7228415251],"iteration":608,"passed_time":11.93019663,"remaining_time":7.659617212},
{"learn":[0.7227404969],"iteration":609,"passed_time":11.94928612,"remaining_time":7.639707518},
{"learn":[0.7225602635],"iteration":610,"passed_time":11.96653571,"remaining_time":7.618629119},
{"learn":[0.7223182877],"iteration":611,"passed_time":11.98407279,"remaining_time":7.597745497},
{"learn":[0.7221492363],"iteration":612,"passed_time":12.00119293,"remaining_time":7.576609568},
{"learn":[0.7220143104],"iteration":613,"passed_time":12.01864419,"remaining_time":7.555694879},
{"learn":[0.7218023863],"iteration":614,"passed_time":12.03569903,"remaining_time":7.534543298},
{"learn":[0.7216827285],"iteration":615,"passed_time":12.05301271,"remaining_time":7.513566363},
{"learn":[0.7215271935],"iteration":616,"passed_time":12.07085828,"remaining_time":7.492931477},
{"learn":[0.7212705425],"iteration":617,"passed_time":12.08801029,"remaining_time":7.471876913},
{"learn":[0.721066881],"iteration":618,"passed_time":12.10533109,"remaining_time":7.450938847},
{"learn":[0.7208777371],"iteration":619,"passed_time":12.12278697,"remaining_time":7.430095239},
{"learn":[0.7207133541],"iteration":620,"passed_time":12.14057617,"remaining_time":7.409465971},
{"learn":[0.7206261075],"iteration":621,"passed_time":12.15955583,"remaining_time":7.389569298},
{"learn":[0.7203379281],"iteration":622,"passed_time":12.17748027,"remaining_time":7.36903702},
{"learn":[0.7201936502],"iteration":623,"passed_time":12.1951174,"remaining_time":7.348339969},
{"learn":[0.7200247278],"iteration":624,"passed_time":12.2126589,"remaining_time":7.327595337},
{"learn":[0.7198453005],"iteration":625,"passed_time":12.23002261,"remaining_time":7.306754722},
{"learn":[0.7197173969],"iteration":626,"passed_time":12.24721854,"remaining_time":7.285825381},
{"learn":[0.7195109163],"iteration":627,"passed_time":12.26417172,"remaining_time":7.264764141},
{"learn":[0.719357151],"iteration":628,"passed_time":12.28103966,"remaining_time":7.243665682},
{"learn":[0.7191708665],"iteration":629,"passed_time":12.29819988,"remaining_time":7.222752311},
{"learn":[0.718992462],"iteration":630,"passed_time":12.31565397,"remaining_time":7.202022685},
{"learn":[0.7187799845],"iteration":631,"passed_time":12.33315084,"remaining_time":7.181328339},
{"learn":[0.7186535501],"iteration":632,"passed_time":12.35469396,"remaining_time":7.162990021},
{"learn":[0.7184902862],"iteration":633,"passed_time":12.37434906,"remaining_time":7.143551663},
{"learn":[0.7182469167],"iteration":634,"passed_time":12.39285673,"remaining_time":7.123453082},
{"learn":[0.7180484554],"iteration":635,"passed_time":12.41168477,"remaining_time":7.103542857},
{"learn":[0.7178310712],"iteration":636,"passed_time":12.42882612,"remaining_time":7.082674852},
{"learn":[0.7176369373],"iteration":637,"passed_time":12.44617796,"remaining_time":7.061937963},
{"learn":[0.7175013613],"iteration":638,"passed_time":12.46396595,"remaining_time":7.041458071},
{"learn":[0.7173900987],"iteration":639,"passed_time":12.48134641,"remaining_time":7.020757356},
{"learn":[0.7172055536],"iteration":640,"passed_time":12.4985873,"remaining_time":6.999988829},
{"learn":[0.7170575334],"iteration":641,"passed_time":12.51712118,"remaining_time":6.979952309},
{"learn":[0.716858866],"iteration":642,"passed_time":12.53434631,"remaining_time":6.959193832},
{"learn":[0.7166548694],"iteration":643,"passed_time":12.55239263,"remaining_time":6.938900274},
{"learn":[0.7165158072],"iteration":644,"passed_time":12.57164999,"remaining_time":6.919280227},
{"learn":[0.7162747562],"iteration":645,"passed_time":12.58926386,"remaining_time":6.898760692},
{"learn":[0.7160636418],"iteration":646,"passed_time":12.60714718,"remaining_time":6.878397149},
{"learn":[0.7159294889],"iteration":647,"passed_time":12.62426728,"remaining_time":6.857626671},
{"learn":[0.7157729709],"iteration":648,"passed_time":12.64183432,"remaining_time":6.837109162},
{"learn":[0.7155978538],"iteration":649,"passed_time":12.65907462,"remaining_time":6.816424796},
{"learn":[0.7154576279],"iteration":650,"passed_time":12.67611164,"remaining_time":6.79564203},
{"learn":[0.7153514548],"iteration":651,"passed_time":12.69336573,"remaining_time":6.774986617},
{"learn":[0.7150639011],"iteration":652,"passed_time":12.71102835,"remaining_time":6.75455871},
{"learn":[0.7147972886],"iteration":653,"passed_time":12.72795487,"remaining_time":6.733749825},
{"learn":[0.7146531116],"iteration":654,"passed_time":12.74574257,"remaining_time":6.713406392},
{"learn":[0.7144053039],"iteration":655,"passed_time":12.76537775,"remaining_time":6.694039552},
{"learn":[0.7142005406],"iteration":656,"passed_time":12.78295525,"remaining_time":6.673597641},
{"learn":[0.7140275629],"iteration":657,"passed_time":12.80045692,"remaining_time":6.653125023},
{"learn":[0.7139010836],"iteration":658,"passed_time":12.81780809,"remaining_time":6.632583548},
{"learn":[0.7137204858],"iteration":659,"passed_time":12.83530305,"remaining_time":6.612125813},
{"learn":[0.7136315624],"iteration":660,"passed_time":12.8523579,"remaining_time":6.591451327},
{"learn":[0.7132506179],"iteration":661,"passed_time":12.86994344,"remaining_time":6.571058734},
{"learn":[0.7130867177],"iteration":662,"passed_time":12.88718045,"remaining_time":6.550497452},
{"learn":[0.7128436785],"iteration":663,"passed_time":12.90429525,"remaining_time":6.529884345},
{"learn":[0.7125982146],"iteration":664,"passed_time":12.92206258,"remaining_time":6.509610471},
{"learn":[0.7124694092],"iteration":665,"passed_time":12.93926301,"remaining_time":6.489059825},
{"learn":[0.7123163292],"iteration":666,"passed_time":12.9569635,"remaining_time":6.468768884},
{"learn":[0.7121404964],"iteration":667,"passed_time":12.97622044,"remaining_time":6.449259262},
{"learn":[0.7119045349],"iteration":668,"passed_time":12.99411676,"remaining_time":6.429077203},
{"learn":[0.7117757208],"iteration":669,"passed_time":13.01174601,"remaining_time":6.408770423},
{"learn":[0.7116744227],"iteration":670,"passed_time":13.02916076,"remaining_time":6.388366455},
{"learn":[0.71149958],"iteration":671,"passed_time":13.0462224,"remaining_time":6.36779903},
{"learn":[0.7113174541],"iteration":672,"passed_time":13.06322292,"remaining_time":6.347212326},
{"learn":[0.7111369137],"iteration":673,"passed_time":13.08037664,"remaining_time":6.326710364},
{"learn":[0.7110506591],"iteration":674,"passed_time":13.09789014,"remaining_time":6.30639155},
{"learn":[0.7108182785],"iteration":675,"passed_time":13.11545381,"remaining_time":6.28610508},
{"learn":[0.7105789152],"iteration":676,"passed_time":13.13295306,"remaining_time":6.26579592},
{"learn":[0.7103897624],"iteration":677,"passed_time":13.15019174,"remaining_time":6.245371296},
{"learn":[0.7102792777],"iteration":678,"passed_time":13.16778332,"remaining_time":6.225122893},
{"learn":[0.7101720257],"iteration":679,"passed_time":13.1868271,"remaining_time":6.205565694},
{"learn":[0.7099590471],"iteration":680,"passed_time":13.20557668,"remaining_time":6.185872191},
{"learn":[0.7096802827],"iteration":681,"passed_time":13.223688,"remaining_time":6.165883847},
{"learn":[0.7095165106],"iteration":682,"passed_time":13.24095451,"remaining_time":6.1455089},
{"learn":[0.7092821405],"iteration":683,"passed_time":13.25827885,"remaining_time":6.12516976},
{"learn":[0.709117271],"iteration":684,"passed_time":13.27522049,"remaining_time":6.104663438},
{"learn":[0.7089012746],"iteration":685,"passed_time":13.29305556,"remaining_time":6.084576454},
{"learn":[0.7087605172],"iteration":686,"passed_time":13.31025074,"remaining_time":6.064204487},
{"learn":[0.7085180442],"iteration":687,"passed_time":13.32888058,"remaining_time":6.044492356},
{"learn":[0.7084211743],"iteration":688,"passed_time":13.34661445,"remaining_time":6.024378946},
{"learn":[0.7082660362],"iteration":689,"passed_time":13.36357972,"remaining_time":6.003927119},
{"learn":[0.7081840709],"iteration":690,"passed_time":13.38164107,"remaining_time":5.983975531},
{"learn":[0.7080233788],"iteration":691,"passed_time":13.40085943,"remaining_time":5.964544373},
{"learn":[0.7078282106],"iteration":692,"passed_time":13.41993109,"remaining_time":5.945048839},
{"learn":[0.707680841],"iteration":693,"passed_time":13.43847643,"remaining_time":5.925322462},
{"learn":[0.7075720933],"iteration":694,"passed_time":13.45647433,"remaining_time":5.90535924},
{"learn":[0.7073908106],"iteration":695,"passed_time":13.47462327,"remaining_time":5.885467636},
{"learn":[0.707086444],"iteration":696,"passed_time":13.49220298,"remaining_time":5.865333576},
{"learn":[0.7069399482],"iteration":697,"passed_time":13.50981356,"remaining_time":5.845220193},
{"learn":[0.706783653],"iteration":698,"passed_time":13.5274216,"remaining_time":5.825112877},
{"learn":[0.7066579178],"iteration":699,"passed_time":13.5450276,"remaining_time":5.805011827},
{"learn":[0.7064536976],"iteration":700,"passed_time":13.56225273,"remaining_time":5.784755444},
{"learn":[0.7062684745],"iteration":701,"passed_time":13.57994352,"remaining_time":5.764705367},
{"learn":[0.706115736],"iteration":702,"passed_time":13.59815274,"remaining_time":5.744881031},
{"learn":[0.7059499143],"iteration":703,"passed_time":13.61772772,"remaining_time":5.725635518},
{"learn":[0.7057697205],"iteration":704,"passed_time":13.63637268,"remaining_time":5.705999916},
{"learn":[0.7056222111],"iteration":705,"passed_time":13.65338336,"remaining_time":5.685686557},
{"learn":[0.7054051278],"iteration":706,"passed_time":13.67032593,"remaining_time":5.665354309},
{"learn":[0.7052870674],"iteration":707,"passed_time":13.68742561,"remaining_time":5.645096437},
{"learn":[0.7049626642],"iteration":708,"passed_time":13.70496431,"remaining_time":5.625027666},
{"learn":[0.70473502],"iteration":709,"passed_time":13.72255923,"remaining_time":5.604988981},
{"learn":[0.7045330474],"iteration":710,"passed_time":13.74011869,"remaining_time":5.584942757},
{"learn":[0.7043864823],"iteration":711,"passed_time":13.75732645,"remaining_time":5.564761259},
{"learn":[0.7041729459],"iteration":712,"passed_time":13.77482203,"remaining_time":5.544703959},
{"learn":[0.7039884112],"iteration":713,"passed_time":13.79259348,"remaining_time":5.524764336},
{"learn":[0.7038419812],"iteration":714,"passed_time":13.81007532,"remaining_time":5.504715336},
{"learn":[0.7036494298],"iteration":715,"passed_time":13.82907352,"remaining_time":5.485274971},
{"learn":[0.7034543313],"iteration":716,"passed_time":13.84738032,"remaining_time":5.465562945},
{"learn":[0.7033107936],"iteration":717,"passed_time":13.86491428,"remaining_time":5.445551292},
{"learn":[0.7031292212],"iteration":718,"passed_time":13.88234104,"remaining_time":5.425504633},
{"learn":[0.7029500698],"iteration":719,"passed_time":13.89966208,"remaining_time":5.405424144},
{"learn":[0.7027699685],"iteration":720,"passed_time":13.91690126,"remaining_time":5.385319628},
{"learn":[0.7026282853],"iteration":721,"passed_time":13.93447005,"remaining_time":5.365349964},
{"learn":[0.7025128219],"iteration":722,"passed_time":13.95139607,"remaining_time":5.34514068},
{"learn":[0.7023302584],"iteration":723,"passed_time":13.96853475,"remaining_time":5.325021535},
{"learn":[0.7021980234],"iteration":724,"passed_time":13.98545869,"remaining_time":5.304829157},
{"learn":[0.7019904278],"iteration":725,"passed_time":14.00304198,"remaining_time":5.284894631},
{"learn":[0.7018075181],"iteration":726,"passed_time":14.0206741,"remaining_time":5.264984909},
{"learn":[0.701655578],"iteration":727,"passed_time":14.0400922,"remaining_time":5.245748735},
{"learn":[0.7013922081],"iteration":728,"passed_time":14.05809535,"remaining_time":5.225986064},
{"learn":[0.7012056398],"iteration":729,"passed_time":14.07546636,"remaining_time":5.205994407},
{"learn":[0.7010531043],"iteration":730,"passed_time":14.09283528,"remaining_time":5.186009153},
{"learn":[0.7009539008],"iteration":731,"passed_time":14.11012529,"remaining_time":5.166002155},
{"learn":[0.7007844665],"iteration":732,"passed_time":14.12735734,"remaining_time":5.14598146},
{"learn":[0.7006447125],"iteration":733,"passed_time":14.14450523,"remaining_time":5.125937862},
{"learn":[0.7004828927],"iteration":734,"passed_time":14.16175465,"remaining_time":5.105938753},
{"learn":[0.7003226756],"iteration":735,"passed_time":14.17930336,"remaining_time":5.086054467},
{"learn":[0.7001517851],"iteration":736,"passed_time":14.19677907,"remaining_time":5.066150469},
{"learn":[0.6999982142],"iteration":737,"passed_time":14.21406412,"remaining_time":5.046185366},
{"learn":[0.6997551188],"iteration":738,"passed_time":14.23192128,"remaining_time":5.026429571},
{"learn":[0.6996463923],"iteration":739,"passed_time":14.27391588,"remaining_time":5.015159633},
{"learn":[0.6994636356],"iteration":740,"passed_time":14.30273367,"remaining_time":4.999201107},
{"learn":[0.6993072298],"iteration":741,"passed_time":14.32616743,"remaining_time":4.981335846},
{"learn":[0.6991587492],"iteration":742,"passed_time":14.34336803,"remaining_time":4.961299573},
{"learn":[0.6989459042],"iteration":743,"passed_time":14.36140576,"remaining_time":4.941558971},
{"learn":[0.6988031979],"iteration":744,"passed_time":14.37876514,"remaining_time":4.921590753},
{"learn":[0.6983818266],"iteration":745,"passed_time":14.39661413,"remaining_time":4.901796232},
{"learn":[0.6982982537],"iteration":746,"passed_time":14.41420554,"remaining_time":4.881919682},
{"learn":[0.6981689219],"iteration":747,"passed_time":14.43155351,"remaining_time":4.861967225},
{"learn":[0.6980143612],"iteration":748,"passed_time":14.45017856,"remaining_time":4.842449689},
{"learn":[0.6978071756],"iteration":749,"passed_time":14.46967282,"remaining_time":4.823224274},
{"learn":[0.6976216431],"iteration":750,"passed_time":14.48792426,"remaining_time":4.803586072},
{"learn":[0.6973539868],"iteration":751,"passed_time":14.50624777,"remaining_time":4.783975329},
{"learn":[0.6972150996],"iteration":752,"passed_time":14.52456545,"remaining_time":4.764366092},
{"learn":[0.6971128499],"iteration":753,"passed_time":14.54303792,"remaining_time":4.744810781},
{"learn":[0.6969446027],"iteration":754,"passed_time":14.56095812,"remaining_time":4.725079125},
{"learn":[0.6968744303],"iteration":755,"passed_time":14.57804413,"remaining_time":4.705083027},
{"learn":[0.6967616212],"iteration":756,"passed_time":14.59519194,"remaining_time":4.685114453},
{"learn":[0.6966824386],"iteration":757,"passed_time":14.61245224,"remaining_time":4.665189237},
{"learn":[0.6965511654],"iteration":758,"passed_time":14.62938172,"remaining_time":4.645165999},
{"learn":[0.6964202234],"iteration":759,"passed_time":14.64654739,"remaining_time":4.625225493},
{"learn":[0.6962846565],"iteration":760,"passed_time":14.66513423,"remaining_time":4.60573861},
{"learn":[0.696126911],"iteration":761,"passed_time":14.68446122,"remaining_time":4.586485262},
{"learn":[0.6959760853],"iteration":762,"passed_time":14.70194697,"remaining_time":4.566659805},
{"learn":[0.6957240805],"iteration":763,"passed_time":14.72004828,"remaining_time":4.547030621},
{"learn":[0.6956280984],"iteration":764,"passed_time":14.73724783,"remaining_time":4.52712842},
{"learn":[0.6955299625],"iteration":765,"passed_time":14.75459709,"remaining_time":4.507279007},
{"learn":[0.6953736067],"iteration":766,"passed_time":14.77185531,"remaining_time":4.487408457},
{"learn":[0.6952221015],"iteration":767,"passed_time":14.78897949,"remaining_time":4.46750422},
{"learn":[0.695067651],"iteration":768,"passed_time":14.80609946,"remaining_time":4.44760595},
{"learn":[0.6948799004],"iteration":769,"passed_time":14.82350538,"remaining_time":4.427800309},
{"learn":[0.694650608],"iteration":770,"passed_time":14.84086664,"remaining_time":4.407987626},
{"learn":[0.6944547618],"iteration":771,"passed_time":14.85838593,"remaining_time":4.388227968},
{"learn":[0.6943329556],"iteration":772,"passed_time":14.87624104,"remaining_time":4.368572725},
{"learn":[0.6941730855],"iteration":773,"passed_time":14.89343818,"remaining_time":4.348730011},
{"learn":[0.6940640372],"iteration":774,"passed_time":14.91227343,"remaining_time":4.329369704},
{"learn":[0.6939399628],"iteration":775,"passed_time":14.93032028,"remaining_time":4.309783175},
{"learn":[0.6937986522],"iteration":776,"passed_time":14.94783633,"remaining_time":4.290048264},
{"learn":[0.6936432483],"iteration":777,"passed_time":14.96536441,"remaining_time":4.270322492},
{"learn":[0.6934625301],"iteration":778,"passed_time":14.98248601,"remaining_time":4.250487044},
{"learn":[0.6933233794],"iteration":779,"passed_time":15.00004946,"remaining_time":4.230783182},
{"learn":[0.6931576552],"iteration":780,"passed_time":15.0177605,"remaining_time":4.211126184},
{"learn":[0.6930317658],"iteration":781,"passed_time":15.03529437,"remaining_time":4.191424774},
{"learn":[0.6929070262],"iteration":782,"passed_time":15.05347319,"remaining_time":4.171907639},
{"learn":[0.6927369051],"iteration":783,"passed_time":15.07173349,"remaining_time":4.152416371},
{"learn":[0.6925419538],"iteration":784,"passed_time":15.09107835,"remaining_time":4.133225281},
{"learn":[0.6924185507],"iteration":785,"passed_time":15.11144084,"remaining_time":4.114310865},
{"learn":[0.6922853549],"iteration":786,"passed_time":15.13061429,"remaining_time":4.095070956},
{"learn":[0.6921567716],"iteration":787,"passed_time":15.14962474,"remaining_time":4.075787365},
{"learn":[0.6919409603],"iteration":788,"passed_time":15.16787546,"remaining_time":4.056301296},
{"learn":[0.6918243614],"iteration":789,"passed_time":15.18737427,"remaining_time":4.037150123},
{"learn":[0.6916809678],"iteration":790,"passed_time":15.20566462,"remaining_time":4.017678768},
{"learn":[0.6914558782],"iteration":791,"passed_time":15.22457241,"remaining_time":3.998372552},
{"learn":[0.6912722877],"iteration":792,"passed_time":15.24281018,"remaining_time":3.978892442},
{"learn":[0.6911242713],"iteration":793,"passed_time":15.26176988,"remaining_time":3.959602764},
{"learn":[0.6909930636],"iteration":794,"passed_time":15.27986811,"remaining_time":3.940091777},
{"learn":[0.6908873703],"iteration":795,"passed_time":15.29803188,"remaining_time":3.920601135},
{"learn":[0.6907418426],"iteration":796,"passed_time":15.31643343,"remaining_time":3.901174388},
{"learn":[0.6905542461],"iteration":797,"passed_time":15.34398156,"remaining_time":3.884065507},
{"learn":[0.6904820549],"iteration":798,"passed_time":15.36617661,"remaining_time":3.865583854},
{"learn":[0.6902877476],"iteration":799,"passed_time":15.38474099,"remaining_time":3.846185249},
{"learn":[0.6901877058],"iteration":800,"passed_time":15.40297043,"remaining_time":3.826705512},
{"learn":[0.6900542702],"iteration":801,"passed_time":15.42184863,"remaining_time":3.807389064},
{"learn":[0.6899368044],"iteration":802,"passed_time":15.44055293,"remaining_time":3.788031042},
{"learn":[0.6898223983],"iteration":803,"passed_time":15.45880774,"remaining_time":3.76856507},
{"learn":[0.6896757529],"iteration":804,"passed_time":15.47733212,"remaining_time":3.749167408},
{"learn":[0.6895071683],"iteration":805,"passed_time":15.49601142,"remaining_time":3.729809199},
{"learn":[0.6893570643],"iteration":806,"passed_time":15.51458072,"remaining_time":3.710426367},
{"learn":[0.6892316331],"iteration":807,"passed_time":15.53512516,"remaining_time":3.691514889},
{"learn":[0.6891022647],"iteration":808,"passed_time":15.55574443,"remaining_time":3.672617041},
{"learn":[0.6890147921],"iteration":809,"passed_time":15.57565377,"remaining_time":3.653548414},
{"learn":[0.6888561034],"iteration":810,"passed_time":15.59495437,"remaining_time":3.634335853},
{"learn":[0.6887608228],"iteration":811,"passed_time":15.61399436,"remaining_time":3.615062735},
{"learn":[0.6886304539],"iteration":812,"passed_time":15.63267154,"remaining_time":3.595706737},
{"learn":[0.6885095512],"iteration":813,"passed_time":15.6504779,"remaining_time":3.576153427},
{"learn":[0.6883600225],"iteration":814,"passed_time":15.6682966,"remaining_time":3.556607204},
{"learn":[0.6882098641],"iteration":815,"passed_time":15.68603868,"remaining_time":3.537047937},
{"learn":[0.6880512657],"iteration":816,"passed_time":15.70385562,"remaining_time":3.517509889},
{"learn":[0.6878377836],"iteration":817,"passed_time":15.72319169,"remaining_time":3.498314043},
{"learn":[0.687631471],"iteration":818,"passed_time":15.7418319,"remaining_time":3.478964071},
{"learn":[0.6873806887],"iteration":819,"passed_time":15.76249167,"remaining_time":3.460059148},
{"learn":[0.6871959235],"iteration":820,"passed_time":15.78120318,"remaining_time":3.440725175},
{"learn":[0.687068458],"iteration":821,"passed_time":15.79928816,"remaining_time":3.421257046},
{"learn":[0.6869239389],"iteration":822,"passed_time":15.81713173,"remaining_time":3.40174036},
{"learn":[0.6867047669],"iteration":823,"passed_time":15.83481339,"remaining_time":3.382193151},
{"learn":[0.6865626342],"iteration":824,"passed_time":15.85276204,"remaining_time":3.3627071},
{"learn":[0.6864501804],"iteration":825,"passed_time":15.87032775,"remaining_time":3.343144102},
{"learn":[0.6862867027],"iteration":826,"passed_time":15.88898596,"remaining_time":3.323814476},
{"learn":[0.686009481],"iteration":827,"passed_time":15.90727594,"remaining_time":3.304409977},
{"learn":[0.6858858117],"iteration":828,"passed_time":15.92642084,"remaining_time":3.285184516},
{"learn":[0.6857099468],"iteration":829,"passed_time":15.94493756,"remaining_time":3.265830584},
{"learn":[0.6855047729],"iteration":830,"passed_time":15.96551337,"remaining_time":3.246897425},
{"learn":[0.6854095966],"iteration":831,"passed_time":15.98349444,"remaining_time":3.227436378},
{"learn":[0.6851548181],"iteration":832,"passed_time":16.00179738,"remaining_time":3.208043411},
{"learn":[0.6848585733],"iteration":833,"passed_time":16.02037451,"remaining_time":3.188707636},
{"learn":[0.6847571193],"iteration":834,"passed_time":16.03861782,"remaining_time":3.169307712},
{"learn":[0.684631162],"iteration":835,"passed_time":16.05731186,"remaining_time":3.149998978},
{"learn":[0.6844527419],"iteration":836,"passed_time":16.07532976,"remaining_time":3.130560037},
{"learn":[0.6842837259],"iteration":837,"passed_time":16.09322929,"remaining_time":3.111101605},
{"learn":[0.6841523715],"iteration":838,"passed_time":16.11021481,"remaining_time":3.091471495},
{"learn":[0.684006947],"iteration":839,"passed_time":16.1273989,"remaining_time":3.071885505},
{"learn":[0.6838632258],"iteration":840,"passed_time":16.14553168,"remaining_time":3.052484585},
{"learn":[0.6837252858],"iteration":841,"passed_time":16.16541939,"remaining_time":3.03341599},
{"learn":[0.6834574412],"iteration":842,"passed_time":16.18376649,"remaining_time":3.014058527},
{"learn":[0.683307741],"iteration":843,"passed_time":16.20116007,"remaining_time":2.994527217},
{"learn":[0.6831930108],"iteration":844,"passed_time":16.21891586,"remaining_time":2.975067406},
{"learn":[0.6830799213],"iteration":845,"passed_time":16.23656035,"remaining_time":2.955591365},
{"learn":[0.6829653542],"iteration":846,"passed_time":16.25642078,"remaining_time":2.936519928},
{"learn":[0.6828763624],"iteration":847,"passed_time":16.27863525,"remaining_time":2.917868582},
{"learn":[0.6827776383],"iteration":848,"passed_time":16.30166956,"remaining_time":2.899354657},
{"learn":[0.6826879071],"iteration":849,"passed_time":16.32074397,"remaining_time":2.880131289},
{"learn":[0.6825687625],"iteration":850,"passed_time":16.33933893,"remaining_time":2.860824326},
{"learn":[0.6821667283],"iteration":851,"passed_time":16.35896028,"remaining_time":2.841697326},
{"learn":[0.6820100406],"iteration":852,"passed_time":16.37776082,"remaining_time":2.822427715},
{"learn":[0.6819074462],"iteration":853,"passed_time":16.39555185,"remaining_time":2.802986617},
{"learn":[0.6817344921],"iteration":854,"passed_time":16.41348188,"remaining_time":2.783572951},
{"learn":[0.6814706619],"iteration":855,"passed_time":16.43187235,"remaining_time":2.764240209},
{"learn":[0.681375795],"iteration":856,"passed_time":16.44994909,"remaining_time":2.744857315},
{"learn":[0.6812390279],"iteration":857,"passed_time":16.46990792,"remaining_time":2.725788957},
{"learn":[0.6809888717],"iteration":858,"passed_time":16.48988542,"remaining_time":2.706721589},
{"learn":[0.6808330912],"iteration":859,"passed_time":16.50841989,"remaining_time":2.687417191},
{"learn":[0.6807189586],"iteration":860,"passed_time":16.52737793,"remaining_time":2.668182964},
{"learn":[0.6805437741],"iteration":861,"passed_time":16.54554078,"remaining_time":2.648822074},
{"learn":[0.6803705921],"iteration":862,"passed_time":16.5642342,"remaining_time":2.629548187},
{"learn":[0.6801486194],"iteration":863,"passed_time":16.58553487,"remaining_time":2.610686044},
{"learn":[0.6799784486],"iteration":864,"passed_time":16.60513242,"remaining_time":2.591552459},
{"learn":[0.6798426208],"iteration":865,"passed_time":16.6239265,"remaining_time":2.572293478},
{"learn":[0.679685449],"iteration":866,"passed_time":16.64327461,"remaining_time":2.553120557},
{"learn":[0.6795160532],"iteration":867,"passed_time":16.66195991,"remaining_time":2.533846437},
{"learn":[0.6794530346],"iteration":868,"passed_time":16.68080915,"remaining_time":2.514598388},
{"learn":[0.6792933494],"iteration":869,"passed_time":16.69993068,"remaining_time":2.495391941},
{"learn":[0.6791978883],"iteration":870,"passed_time":16.71880418,"remaining_time":2.476148954},
{"learn":[0.6789641377],"iteration":871,"passed_time":16.73746677,"remaining_time":2.456875856},
{"learn":[0.6788818877],"iteration":872,"passed_time":16.75606048,"remaining_time":2.437594137},
{"learn":[0.6788239765],"iteration":873,"passed_time":16.77503506,"remaining_time":2.418368899},
{"learn":[0.6787060717],"iteration":874,"passed_time":16.7959167,"remaining_time":2.399416671},
{"learn":[0.6786126443],"iteration":875,"passed_time":16.81460741,"remaining_time":2.380149907},
{"learn":[0.6784715889],"iteration":876,"passed_time":16.83373115,"remaining_time":2.360945189},
{"learn":[0.6783026244],"iteration":877,"passed_time":16.85305471,"remaining_time":2.341768422},
{"learn":[0.6781345861],"iteration":878,"passed_time":16.87139973,"remaining_time":2.322456618},
{"learn":[0.6779447024],"iteration":879,"passed_time":16.88966045,"remaining_time":2.303135516},
{"learn":[0.6777677186],"iteration":880,"passed_time":16.90801088,"remaining_time":2.283828939},
{"learn":[0.6776908903],"iteration":881,"passed_time":16.92619394,"remaining_time":2.264502138},
{"learn":[0.6775542727],"iteration":882,"passed_time":16.94456925,"remaining_time":2.2452034},
{"learn":[0.6774507386],"iteration":883,"passed_time":16.96268552,"remaining_time":2.225872761},
{"learn":[0.677343073],"iteration":884,"passed_time":16.98176897,"remaining_time":2.206670544},
{"learn":[0.6772096483],"iteration":885,"passed_time":17.00100141,"remaining_time":2.187487767},
{"learn":[0.677005987],"iteration":886,"passed_time":17.01891003,"remaining_time":2.168136227},
{"learn":[0.6768574185],"iteration":887,"passed_time":17.03646348,"remaining_time":2.148743142},
{"learn":[0.6767263871],"iteration":888,"passed_time":17.05505416,"remaining_time":2.129483702},
{"learn":[0.6764827475],"iteration":889,"passed_time":17.07318193,"remaining_time":2.110168553},
{"learn":[0.676376315],"iteration":890,"passed_time":17.09164636,"remaining_time":2.090897253},
{"learn":[0.6762630085],"iteration":891,"passed_time":17.10861375,"remaining_time":2.071446508},
{"learn":[0.6761836034],"iteration":892,"passed_time":17.12545498,"remaining_time":2.051986207},
{"learn":[0.6760901271],"iteration":893,"passed_time":17.14227217,"remaining_time":2.032528915},
{"learn":[0.6757937791],"iteration":894,"passed_time":17.15986079,"remaining_time":2.013168026},
{"learn":[0.6756631151],"iteration":895,"passed_time":17.17737,"remaining_time":1.993801875},
{"learn":[0.6755207374],"iteration":896,"passed_time":17.19629091,"remaining_time":1.974601967},
{"learn":[0.6754363121],"iteration":897,"passed_time":17.21408099,"remaining_time":1.955274233},
{"learn":[0.6752606962],"iteration":898,"passed_time":17.23182752,"remaining_time":1.935945028},
{"learn":[0.6751578905],"iteration":899,"passed_time":17.24882604,"remaining_time":1.916536227},
{"learn":[0.6750533139],"iteration":900,"passed_time":17.26562782,"remaining_time":1.897111158},
{"learn":[0.6749701732],"iteration":901,"passed_time":17.28302894,"remaining_time":1.877757025},
{"learn":[0.674795199],"iteration":902,"passed_time":17.30030479,"remaining_time":1.858393759},
{"learn":[0.6747214419],"iteration":903,"passed_time":17.31761463,"remaining_time":1.839038721},
{"learn":[0.6745940675],"iteration":904,"passed_time":17.33485901,"remaining_time":1.819681333},
{"learn":[0.6744582237],"iteration":905,"passed_time":17.3518574,"remaining_time":1.800303086},
{"learn":[0.6743167014],"iteration":906,"passed_time":17.36869389,"remaining_time":1.780913485},
{"learn":[0.674202307],"iteration":907,"passed_time":17.38619455,"remaining_time":1.761596805},
{"learn":[0.6740803925],"iteration":908,"passed_time":17.40396638,"remaining_time":1.742311266},
{"learn":[0.673960633],"iteration":909,"passed_time":17.4230622,"remaining_time":1.723159998},
{"learn":[0.6737908111],"iteration":910,"passed_time":17.44037296,"remaining_time":1.70383446},
{"learn":[0.6736389154],"iteration":911,"passed_time":17.45776121,"remaining_time":1.684520819},
{"learn":[0.6735220343],"iteration":912,"passed_time":17.47488123,"remaining_time":1.665185834},
{"learn":[0.6732766839],"iteration":913,"passed_time":17.49229585,"remaining_time":1.645883417},
{"learn":[0.6732118733],"iteration":914,"passed_time":17.50958603,"remaining_time":1.626573566},
{"learn":[0.6730883269],"iteration":915,"passed_time":17.52643651,"remaining_time":1.607227802},
{"learn":[0.6729927562],"iteration":916,"passed_time":17.54331295,"remaining_time":1.587889831},
{"learn":[0.6728724924],"iteration":917,"passed_time":17.56049779,"remaining_time":1.56858477},
{"learn":[0.6727473964],"iteration":918,"passed_time":17.57741236,"remaining_time":1.549260501},
{"learn":[0.6726307913],"iteration":919,"passed_time":17.59514652,"remaining_time":1.53001274},
{"learn":[0.6725159164],"iteration":920,"passed_time":17.61252273,"remaining_time":1.510737563},
{"learn":[0.6724343859],"iteration":921,"passed_time":17.63264714,"remaining_time":1.491698999},
{"learn":[0.6723413454],"iteration":922,"passed_time":17.65023456,"remaining_time":1.472446437},
{"learn":[0.6722490892],"iteration":923,"passed_time":17.66735724,"remaining_time":1.453159253},
{"learn":[0.6721320464],"iteration":924,"passed_time":17.68504007,"remaining_time":1.433922167},
{"learn":[0.6719669502],"iteration":925,"passed_time":17.7066011,"remaining_time":1.41499836},
{"learn":[0.6718185552],"iteration":926,"passed_time":17.72486482,"remaining_time":1.395809204},
{"learn":[0.6717229918],"iteration":927,"passed_time":17.74257044,"remaining_time":1.376578741},
{"learn":[0.6714823426],"iteration":928,"passed_time":17.76064363,"remaining_time":1.357379653},
{"learn":[0.6713519599],"iteration":929,"passed_time":17.77787893,"remaining_time":1.33811992},
{"learn":[0.671187639],"iteration":930,"passed_time":17.79614616,"remaining_time":1.318941015},
{"learn":[0.6710758831],"iteration":931,"passed_time":17.81394544,"remaining_time":1.299729925},
{"learn":[0.6708259088],"iteration":932,"passed_time":17.83336555,"remaining_time":1.280638255},
{"learn":[0.6706792271],"iteration":933,"passed_time":17.85071551,"remaining_time":1.261399597},
{"learn":[0.6705049196],"iteration":934,"passed_time":17.86788865,"remaining_time":1.242152687},
{"learn":[0.6703411273],"iteration":935,"passed_time":17.88501958,"remaining_time":1.222907321},
{"learn":[0.6701844163],"iteration":936,"passed_time":17.902476,"remaining_time":1.203688354},
{"learn":[0.6700546896],"iteration":937,"passed_time":17.91998287,"remaining_time":1.18447648},
{"learn":[0.66990457],"iteration":938,"passed_time":17.93707601,"remaining_time":1.16524136},
{"learn":[0.669753602],"iteration":939,"passed_time":17.95413961,"remaining_time":1.146008911},
{"learn":[0.6695851471],"iteration":940,"passed_time":17.97202093,"remaining_time":1.126832343},
{"learn":[0.6694327994],"iteration":941,"passed_time":17.98926052,"remaining_time":1.107619013},
{"learn":[0.6691149262],"iteration":942,"passed_time":18.00685594,"remaining_time":1.088431377},
{"learn":[0.6689638009],"iteration":943,"passed_time":18.02461951,"remaining_time":1.06925709},
{"learn":[0.6688679633],"iteration":944,"passed_time":18.04347255,"remaining_time":1.050149196},
{"learn":[0.66879575],"iteration":945,"passed_time":18.06105109,"remaining_time":1.03096909},
{"learn":[0.6686112803],"iteration":946,"passed_time":18.07808894,"remaining_time":1.011762106},
{"learn":[0.6684815777],"iteration":947,"passed_time":18.09532449,"remaining_time":0.9925705419},
{"learn":[0.6683817409],"iteration":948,"passed_time":18.11269687,"remaining_time":0.9733904537},
{"learn":[0.6682864263],"iteration":949,"passed_time":18.13003342,"remaining_time":0.9542122854},
{"learn":[0.6681745748],"iteration":950,"passed_time":18.14709227,"remaining_time":0.9350236817},
{"learn":[0.6680346061],"iteration":951,"passed_time":18.1643742,"remaining_time":0.9158507998},
{"learn":[0.6678953834],"iteration":952,"passed_time":18.18127568,"remaining_time":0.8966631236},
{"learn":[0.6677052842],"iteration":953,"passed_time":18.19803678,"remaining_time":0.8774734718},
{"learn":[0.6675235769],"iteration":954,"passed_time":18.21648167,"remaining_time":0.8583682463},
{"learn":[0.6674514229],"iteration":955,"passed_time":18.2338523,"remaining_time":0.8392149595},
{"learn":[0.6673166089],"iteration":956,"passed_time":18.25357498,"remaining_time":0.8201710805},
{"learn":[0.6671736242],"iteration":957,"passed_time":18.27102986,"remaining_time":0.8010263611},
{"learn":[0.6670343076],"iteration":958,"passed_time":18.2882292,"remaining_time":0.7818742411},
{"learn":[0.6669309082],"iteration":959,"passed_time":18.30532292,"remaining_time":0.7627217884},
{"learn":[0.6668083839],"iteration":960,"passed_time":18.32259222,"remaining_time":0.7435807458},
{"learn":[0.6666486395],"iteration":961,"passed_time":18.34025155,"remaining_time":0.724459001},
{"learn":[0.666560112],"iteration":962,"passed_time":18.35708628,"remaining_time":0.7053086111},
{"learn":[0.6663185854],"iteration":963,"passed_time":18.37434892,"remaining_time":0.6861790052},
{"learn":[0.6661983438],"iteration":964,"passed_time":18.39175813,"remaining_time":0.667058585},
{"learn":[0.6660441193],"iteration":965,"passed_time":18.409332,"remaining_time":0.6479475032},
{"learn":[0.6659106625],"iteration":966,"passed_time":18.42639589,"remaining_time":0.628822197},
{"learn":[0.6657888949],"iteration":967,"passed_time":18.44413155,"remaining_time":0.6097233571},
{"learn":[0.6656544192],"iteration":968,"passed_time":18.46330933,"remaining_time":0.5906734667},
{"learn":[0.6654969391],"iteration":969,"passed_time":18.48125807,"remaining_time":0.571585301},
{"learn":[0.6653265928],"iteration":970,"passed_time":18.49860232,"remaining_time":0.5524814288},
{"learn":[0.6650535053],"iteration":971,"passed_time":18.51679872,"remaining_time":0.5334057244},
{"learn":[0.6649327067],"iteration":972,"passed_time":18.53389657,"remaining_time":0.5143013435},
{"learn":[0.664824046],"iteration":973,"passed_time":18.55096008,"remaining_time":0.4952001664},
{"learn":[0.6647149264],"iteration":974,"passed_time":18.56783385,"remaining_time":0.4760983039},
{"learn":[0.6646559837],"iteration":975,"passed_time":18.58492641,"remaining_time":0.4570063871},
{"learn":[0.6645670001],"iteration":976,"passed_time":18.60217642,"remaining_time":0.4379222698},
{"learn":[0.6644219575],"iteration":977,"passed_time":18.61947263,"remaining_time":0.4188429427},
{"learn":[0.6643020237],"iteration":978,"passed_time":18.63671869,"remaining_time":0.3997661822},
{"learn":[0.6641368167],"iteration":979,"passed_time":18.65458026,"remaining_time":0.3807057195},
{"learn":[0.6638814883],"iteration":980,"passed_time":18.67410282,"remaining_time":0.3616798711},
{"learn":[0.663725018],"iteration":981,"passed_time":18.69178219,"remaining_time":0.3426192254},
{"learn":[0.6636157064],"iteration":982,"passed_time":18.70934927,"remaining_time":0.3235594482},
{"learn":[0.6634169501],"iteration":983,"passed_time":18.7265834,"remaining_time":0.3044972911},
{"learn":[0.6633613986],"iteration":984,"passed_time":18.74415003,"remaining_time":0.285443909},
{"learn":[0.6632777797],"iteration":985,"passed_time":18.76129587,"remaining_time":0.2663875682},
{"learn":[0.6631674107],"iteration":986,"passed_time":18.77952322,"remaining_time":0.2473493434},
{"learn":[0.6630275269],"iteration":987,"passed_time":18.7973988,"remaining_time":0.2283084874},
{"learn":[0.662851118],"iteration":988,"passed_time":18.81592235,"remaining_time":0.209277195},
{"learn":[0.6626787891],"iteration":989,"passed_time":18.83409578,"remaining_time":0.1902433917},
{"learn":[0.6625530543],"iteration":990,"passed_time":18.85178815,"remaining_time":0.171206956},
{"learn":[0.6623140519],"iteration":991,"passed_time":18.8722663,"remaining_time":0.152195696},
{"learn":[0.6622435728],"iteration":992,"passed_time":18.88988559,"remaining_time":0.1331613285},
{"learn":[0.662090194],"iteration":993,"passed_time":18.90749067,"remaining_time":0.1141297224},
{"learn":[0.6619645069],"iteration":994,"passed_time":18.92508788,"remaining_time":0.09510094412},
{"learn":[0.6617840255],"iteration":995,"passed_time":18.94228102,"remaining_time":0.07607341773},
{"learn":[0.6616198384],"iteration":996,"passed_time":18.95924495,"remaining_time":0.0570488815},
{"learn":[0.6614662755],"iteration":997,"passed_time":18.97657937,"remaining_time":0.03802921718},
{"learn":[0.6613162577],"iteration":998,"passed_time":18.99380855,"remaining_time":0.01901282137},
{"learn":[0.661200028],"iteration":999,"passed_time":19.01086194,"remaining_time":0}
]}